{"artists":[{"id":"03r4iKL2g2442PT9n2UKsx","name":"Beastie Boys","popularity":71,"images":[{"url":"https:\/\/i.scdn.co\/image\/705bcd56dc5dbf9ebc578a3ba8094e6d622862c2","height":771,"width":1000},{"url":"https:\/\/i.scdn.co\/image\/060ef251f0e12353057c36fe94724b688b963dac","height":494,"width":640},{"url":"https:\/\/i.scdn.co\/image\/eb9a69f247e84b9e9ce8b03f1ab5cca399b49cbc","height":154,"width":200},{"url":"https:\/\/i.scdn.co\/image\/b6fafee2c4c169dadf039c2066ab77beb4c82b3e","height":49,"width":64}]},{"id":"3WrFJ7ztbogyGnTHbHJFl2","name":"The Beatles","popularity":86,"images":[{"url":"https:\/\/i.scdn.co\/image\/ab6761610000e5ebe9348cc01ff5d55971b22433","height":640,"width":640},{"url":"https:\/\/i.scdn.co\/image\/ab67616100005174e9348cc01ff5d55971b22433","height":320,"width":320},{"url":"https:\/\/i.scdn.co\/image\/ab6761610000f178e9348cc01ff5d55971b22433","height":160,"width":160}]},{"id":"22wbnEMDvgVIAGdFeek6ET","name":"Benson Boone","popularity":88,"images":[{"url":"https:\/\/i.scdn.co\/image\/ab6761610000e5eb9a39ecd2481c38174aa36260","height":640,"width":640},{"url":"https:\/\/i.scdn.co\/image\/ab676161000051749a39ecd2481c38174aa36260","height":320,"width":320},{"url":"https:\/\/i.scdn.co\/image\/ab6761610000f1789a39ecd2481c38174aa36260","height":160,"width":160}]},{"id":"3Y7RZ31TRPVadSFVy1o8os","name":"H.E.R.","popularity":77,"images":[{"url":"https:\/\/i.scdn.co\/image\/ab6761610000e5eb417db49cde3ed1c5a65e3514","height":640,"width":640},{"url":"https:\/\/i.scdn.co\/image\/ab67616100005174417db49cde3ed1c5a65e3514","height":320,"width":320},{"url":"https:\/\/i.scdn.co\/image\/ab6761610000f178417db49cde3ed1c5a65e3514","height":160,"width":160}]},{"id":"6kACVPfCOnqzgfEF5ryl0x","name":"Johnny Cash","popularity":77,"images":[{"url":"https:\/\/i.scdn.co\/image\/ab6761610000e5eb94a8326675bfcafb20f0a235","height":640,"width":640},{"url":"https:\/\/i.scdn.co\/image\/ab6761610000517494a8326675bfcafb20f0a235","height":320,"width":320},{"url":"https:\/\/i.scdn.co\/image\/ab6761610000f17894a8326675bfcafb20f0a235","height":160,"width":160}]},{"id":"24bEVJfL5KhIf4fYZeIfg7","name":"Besouro Mulher","popularity":29,"images":[{"url":"https:\/\/i.scdn.co\/image\/ab6761610000e5ebeb31bda392914fd41a799606","height":640,"width":640},{"url":"https:\/\/i.scdn.co\/image\/ab67616100005174eb31bda392914fd41a799606","height":320,"width":320},{"url":"https:\/\/i.scdn.co\/image\/ab6761610000f178eb31bda392914fd41a799606","height":160,"width":160}]},{"id":"37DdwREpvvQHmGLFEZ4h0Q","name":"Basshunter","popularity":64,"images":[{"url":"https:\/\/i.scdn.co\/image\/ab6761610000e5ebc54bad2f1330a03cb8aa177d","height":640,"width":640},{"url":"https:\/\/i.scdn.co\/image\/ab67616100005174c54bad2f1330a03cb8aa177d","height":320,"width":320},{"url":"https:\/\/i.scdn.co\/image\/ab6761610000f178c54bad2f1330a03cb8aa177d","height":160,"width":160}]},{"id":"4YrKBkKSVeqDamzBPWVnSJ","name":"Basement Jaxx","popularity":64,"images":[{"url":"https:\/\/i.scdn.co\/image\/ab6761610000e5ebfb07b8d0b7cc60c26de3b145","height":640,"width":640},{"url":"https:\/\/i.scdn.co\/image\/ab67616100005174fb07b8d0b7cc60c26de3b145","height":320,"width":320},{"url":"https:\/\/i.scdn.co\/image\/ab6761610000f178fb07b8d0b7cc60c26de3b145","height":160,"width":160}]},{"id":"619CzMJPPWrCeZwx5qw6ko","name":"Besomorph","popularity":63,"images":[{"url":"https:\/\/i.scdn.co\/image\/ab6761610000e5eb189ba595abd44ba18fbcc9d4","height":640,"width":640},{"url":"https:\/\/i.scdn.co\/image\/ab67616100005174189ba595abd44ba18fbcc9d4","height":320,"width":320},{"url":"https:\/\/i.scdn.co\/image\/ab6761610000f178189ba595abd44ba18fbcc9d4","height":160,"width":160}]},{"id":"7saDvxqzCAwySXjDdlZNqw","name":"Best Noise","popularity":63,"images":[{"url":"https:\/\/i.scdn.co\/image\/ab6761610000e5ebaab2e89271ccb46317315e68","height":640,"width":640},{"url":"https:\/\/i.scdn.co\/image\/ab67616100005174aab2e89271ccb46317315e68","height":320,"width":320},{"url":"https:\/\/i.scdn.co\/image\/ab6761610000f178aab2e89271ccb46317315e68","height":160,"width":160}]}],"albums":[{"id":"3uSWaQxJAdm5MWKQkQJNoK","name":"The Best of Sade","images":[{"height":640,"url":"https:\/\/i.scdn.co\/image\/ab67616d0000b2735e25e034e25258b356774c79","width":640},{"height":300,"url":"https:\/\/i.scdn.co\/image\/ab67616d00001e025e25e034e25258b356774c79","width":300},{"height":64,"url":"https:\/\/i.scdn.co\/image\/ab67616d000048515e25e034e25258b356774c79","width":64}],"artists":[{"id":"47zz7sob9NUcODy0BTDvKx","name":"Sade"}]},{"id":"0WSpHK6tinGHU4gvP8fHih","name":"The Best Of 1980 - 1990","images":[{"height":640,"url":"https:\/\/i.scdn.co\/image\/ab67616d0000b273ba171000f58dd9dde2692122","width":640},{"height":300,"url":"https:\/\/i.scdn.co\/image\/ab67616d00001e02ba171000f58dd9dde2692122","width":300},{"height":64,"url":"https:\/\/i.scdn.co\/image\/ab67616d00004851ba171000f58dd9dde2692122","width":64}],"artists":[{"id":"51Blml2LZPmy7TTiAg47vQ","name":"U2"}]},{"id":"6lqE05fiHWJVYYdMVJNj38","name":"The Best Damn Thing (Expanded Edition)","images":[{"height":640,"url":"https:\/\/i.scdn.co\/image\/ab67616d0000b273476cdf5837ae39eee951cc15","width":640},{"height":300,"url":"https:\/\/i.scdn.co\/image\/ab67616d00001e02476cdf5837ae39eee951cc15","width":300},{"height":64,"url":"https:\/\/i.scdn.co\/image\/ab67616d00004851476cdf5837ae39eee951cc15","width":64}],"artists":[{"id":"0p4nmQO2msCgU4IF37Wi3j","name":"Avril Lavigne"}]},{"id":"5XfjDQo9PArfozuQ5SBSp9","name":"Boy Besta","images":[{"height":640,"url":"https:\/\/i.scdn.co\/image\/ab67616d0000b273320f4a08913b939a8637c301","width":640},{"height":300,"url":"https:\/\/i.scdn.co\/image\/ab67616d00001e02320f4a08913b939a8637c301","width":300},{"height":64,"url":"https:\/\/i.scdn.co\/image\/ab67616d00004851320f4a08913b939a8637c301","width":64}],"artists":[{"id":"6XFc29m1ptfUNmaa1UTuBT","name":"MC Jo\u00e3ozinho VT"},{"id":"4LHTgACY32k94VDjenF0nP","name":"Mc Neg\u00e3o Original"},{"id":"6aoGgTKGqtsjj48ymcNs4Z","name":"MC Tuto"}]},{"id":"26Ua4qkA802fEsHkbOiuex","name":"Bes","images":[{"height":640,"url":"https:\/\/i.scdn.co\/image\/ab67616d0000b2730e1df09281853b66f59ead84","width":640},{"height":300,"url":"https:\/\/i.scdn.co\/image\/ab67616d00001e020e1df09281853b66f59ead84","width":300},{"height":64,"url":"https:\/\/i.scdn.co\/image\/ab67616d000048510e1df09281853b66f59ead84","width":64}],"artists":[{"id":"4hOby8V5qAcpSDTMxKchiR","name":"The Dwarfs of East Agouza"}]},{"id":"1CYiVBStP9np5G7go1Ss6C","name":"Bes","images":[{"height":640,"url":"https:\/\/i.scdn.co\/image\/ab67616d0000b273a3a274dd2d85bfed85d59390","width":640},{"height":300,"url":"https:\/\/i.scdn.co\/image\/ab67616d00001e02a3a274dd2d85bfed85d59390","width":300},{"height":64,"url":"https:\/\/i.scdn.co\/image\/ab67616d00004851a3a274dd2d85bfed85d59390","width":64}],"artists":[{"id":"6gE1Zi3sHbUwZPGGSvQT9p","name":"Igla"},{"id":"1TWluOJESZjl6NqIi8i6RA","name":"Dzu"}]},{"id":"7gRwmpC7lCB5Wy6fj7QAUg","name":"Bes","images":[{"height":640,"url":"https:\/\/i.scdn.co\/image\/ab67616d0000b2730802eb2acf06c2ad9aea7edd","width":640},{"height":300,"url":"https:\/\/i.scdn.co\/image\/ab67616d00001e020802eb2acf06c2ad9aea7edd","width":300},{"height":64,"url":"https:\/\/i.scdn.co\/image\/ab67616d000048510802eb2acf06c2ad9aea7edd","width":64}],"artists":[{"id":"1ArfY8JLfmsjpAJevSsEMP","name":"Nenad Osmanovic"},{"id":"0TQPTssnGiG6NUznNG4W86","name":"Grand Production"}]},{"id":"65uYM9NReKZ33eekX5RiYy","name":"Besos","images":[{"height":640,"url":"https:\/\/i.scdn.co\/image\/ab67616d0000b273ed52d4ebacaf353b4fc20f12","width":640},{"height":300,"url":"https:\/\/i.scdn.co\/image\/ab67616d00001e02ed52d4ebacaf353b4fc20f12","width":300},{"height":64,"url":"https:\/\/i.scdn.co\/image\/ab67616d00004851ed52d4ebacaf353b4fc20f12","width":64}],"artists":[{"id":"0oOet2f43PA68X5RxKobEy","name":"Shreya Ghoshal"},{"id":"4yxICw7joYAxRI2sTRldLB","name":"Rajat Nagpal"},{"id":"1ID8wBJ6PWBtuuERZxavHd","name":"Freebot"}]},{"id":"09gjjKWYhGDKIcn4TAosR5","name":"Bes","images":[{"height":640,"url":"https:\/\/i.scdn.co\/image\/ab67616d0000b273c58221bb82c99adcb787401a","width":640},{"height":300,"url":"https:\/\/i.scdn.co\/image\/ab67616d00001e02c58221bb82c99adcb787401a","width":300},{"height":64,"url":"https:\/\/i.scdn.co\/image\/ab67616d00004851c58221bb82c99adcb787401a","width":64}],"artists":[{"id":"45IEFIHD9y1LtrIw2CLzV1","name":"Sajsi MC"},{"id":"5ev7qvqkzXCzlZIDWvP7is","name":"DJ BKO"}]},{"id":"2go3eo1swIay60KwWojA1y","name":"BEST DUO","images":[{"height":640,"url":"https:\/\/i.scdn.co\/image\/ab67616d0000b27381439ba508f1e7912e50a04e","width":640},{"height":300,"url":"https:\/\/i.scdn.co\/image\/ab67616d00001e0281439ba508f1e7912e50a04e","width":300},{"height":64,"url":"https:\/\/i.scdn.co\/image\/ab67616d0000485181439ba508f1e7912e50a04e","width":64}],"artists":[{"id":"29QKtXMaVczUBDiI3aPBWS","name":"FBC"},{"id":"3bgFgu57tkJSn1ONpK9Gs3","name":"Iza Sabino"},{"id":"2qATSoNFfzMaTEZFfJpG4c","name":"SMU"}]}],"playlists":[{"id":"1puQ0hv40TUre24cFillJS","name":"Best Rock songs of All Time","images":[{"height":null,"url":"https:\/\/image-cdn-ak.spotifycdn.com\/image\/ab67706c0000da84027d6bd3f165839b8eaae213","width":null}]},{"id":"0gqrnk12Q8OExuCeKyBRCq","name":"BEST SONGS OF ALL TIME","images":[{"height":null,"url":"https:\/\/image-cdn-ak.spotifycdn.com\/image\/ab67706c0000da84c307e64446e1e387b9b460b4","width":null}]},{"id":"3lRvb9RIb0MyUTU4O0IZAv","name":"BEST GUITAR SOLOS OF ALL TIME","images":[{"height":640,"url":"https:\/\/mosaic.scdn.co\/640\/ab67616d00001e0217dd812df38fed44d6d2036eab67616d00001e024637341b9f507521afa9a778ab67616d00001e02e3f9acd031d98fcd2e9c802bab67616d00001e02e44963b8bb127552ac761873","width":640},{"height":300,"url":"https:\/\/mosaic.scdn.co\/300\/ab67616d00001e0217dd812df38fed44d6d2036eab67616d00001e024637341b9f507521afa9a778ab67616d00001e02e3f9acd031d98fcd2e9c802bab67616d00001e02e44963b8bb127552ac761873","width":300},{"height":60,"url":"https:\/\/mosaic.scdn.co\/60\/ab67616d00001e0217dd812df38fed44d6d2036eab67616d00001e024637341b9f507521afa9a778ab67616d00001e02e3f9acd031d98fcd2e9c802bab67616d00001e02e44963b8bb127552ac761873","width":60}]},{"id":"6i2Qd6OpeRBAzxfscNXeWp","name":"Top 100 Greatest Songs of All Time","images":[{"height":null,"url":"https:\/\/image-cdn-ak.spotifycdn.com\/image\/ab67706c0000d72c9418dd3e204505b565f1b3fe","width":null}]},{"id":"2rP7cjH0aGECdyRWyK3PcC","name":"BLACK ANTIGOS 2000'S | S\u00d3 OS MELHORES \ud83d\udc8e","images":[{"height":640,"url":"https:\/\/mosaic.scdn.co\/640\/ab67616d00001e027e81fb67084fb59858a43bf2ab67616d00001e0291f7222996c531b981e7bb3dab67616d00001e029b19c107109de740bad72df5ab67616d00001e02f6a0e1e8b3192782bb205cfa","width":640},{"height":300,"url":"https:\/\/mosaic.scdn.co\/300\/ab67616d00001e027e81fb67084fb59858a43bf2ab67616d00001e0291f7222996c531b981e7bb3dab67616d00001e029b19c107109de740bad72df5ab67616d00001e02f6a0e1e8b3192782bb205cfa","width":300},{"height":60,"url":"https:\/\/mosaic.scdn.co\/60\/ab67616d00001e027e81fb67084fb59858a43bf2ab67616d00001e0291f7222996c531b981e7bb3dab67616d00001e029b19c107109de740bad72df5ab67616d00001e02f6a0e1e8b3192782bb205cfa","width":60}]},{"id":"0DrYCIHq60V5DfgTqQXBPR","name":"\u2022 Best Vibe  \u2022","images":[{"height":640,"url":"https:\/\/mosaic.scdn.co\/640\/ab67616d00001e02350ab7a839c04bfd5225a9f5ab67616d00001e0246ca0b648bdaf6047dc50efdab67616d00001e024ae1c4c5c45aabe565499163ab67616d00001e027a9bf5f82e32d33d4503fe7b","width":640},{"height":300,"url":"https:\/\/mosaic.scdn.co\/300\/ab67616d00001e02350ab7a839c04bfd5225a9f5ab67616d00001e0246ca0b648bdaf6047dc50efdab67616d00001e024ae1c4c5c45aabe565499163ab67616d00001e027a9bf5f82e32d33d4503fe7b","width":300},{"height":60,"url":"https:\/\/mosaic.scdn.co\/60\/ab67616d00001e02350ab7a839c04bfd5225a9f5ab67616d00001e0246ca0b648bdaf6047dc50efdab67616d00001e024ae1c4c5c45aabe565499163ab67616d00001e027a9bf5f82e32d33d4503fe7b","width":60}]},{"id":"6kc7xc4S1F2SRzc57Umhvz","name":"BRAZILIAN PHONK VIRAL 2025 \ud83d\udc80\ud83c\udde7\ud83c\uddf7","images":[{"height":null,"url":"https:\/\/image-cdn-ak.spotifycdn.com\/image\/ab67706c0000da8432ab72f8cebef7b7fd49cf0d","width":null}]},{"id":"1MqWvDzQRAGi7vKy69YvFV","name":"FLASHBACK :  ANOS 70, 80, 90.","images":[{"height":null,"url":"https:\/\/image-cdn-ak.spotifycdn.com\/image\/ab67706c0000da8453c38c636a9de34c415f89ff","width":null}]}],"podcasts":[{"id":"3IM0lmZxpFAY7CwMuv9H4g","name":"The Daily","publisher":"The New York Times","images":[{"height":640,"url":"https:\/\/i.scdn.co\/image\/ab6765630000ba8ac209144b2c67a524fcbaa70c","width":640},{"height":300,"url":"https:\/\/i.scdn.co\/image\/ab67656300005f1fc209144b2c67a524fcbaa70c","width":300},{"height":64,"url":"https:\/\/i.scdn.co\/image\/ab6765630000f68dc209144b2c67a524fcbaa70c","width":64}]},{"id":"5SproVuGZAf5e88SYy8dlR","name":"2025 House \/ Techno \/ Progressive \/ Deep \/ Melodic \/ Tech \/ Edm \/ Afro \/ ibiza DJ Mix \/ Set \/ Podcast \/ Electronic Dance Music Radio Club 2024 Afterhours Beach Party best top Workout Playlist Tribal Dub Beats Tomorrowland - DJ TEKNESS Sessions","publisher":"DJ TeKness | Techno \/ House & Electronic Dance Music Mixes Beats","images":[{"height":640,"url":"https:\/\/i.scdn.co\/image\/ab6765630000ba8a839327e8a7366f86ea1b4ceb","width":640},{"height":300,"url":"https:\/\/i.scdn.co\/image\/ab67656300005f1f839327e8a7366f86ea1b4ceb","width":300},{"height":64,"url":"https:\/\/i.scdn.co\/image\/ab6765630000f68d839327e8a7366f86ea1b4ceb","width":64}]},{"id":"5slNbyLCLd1DbVY5p19Liw","name":"Best Noise Labs","publisher":"Best Noise","images":[{"height":640,"url":"https:\/\/i.scdn.co\/image\/ab6765630000ba8afe9cba57153eecb918267571","width":640},{"height":300,"url":"https:\/\/i.scdn.co\/image\/ab67656300005f1ffe9cba57153eecb918267571","width":300},{"height":64,"url":"https:\/\/i.scdn.co\/image\/ab6765630000f68dfe9cba57153eecb918267571","width":64}]},{"id":"0LAoyFauqOBsEM7FJFu3Fh","name":"BEST TF MUSIC EDITS\u203c\ufe0f\u203c\ufe0f\ud83d\ude4f [PUT YOUR RECOMMENDATIONS IN THE COMMENTS\u203c\ufe0f\ud83d\udc98]","publisher":"Rodimussy\ud83e\udef6","images":[{"height":640,"url":"https:\/\/i.scdn.co\/image\/ab6765630000ba8a2f00d781ef3b12202b4adbdb","width":640},{"height":300,"url":"https:\/\/i.scdn.co\/image\/ab67656300005f1f2f00d781ef3b12202b4adbdb","width":300},{"height":64,"url":"https:\/\/i.scdn.co\/image\/ab6765630000f68d2f00d781ef3b12202b4adbdb","width":64}]},{"id":"6sdM4HFg9nSxkStCR3AG6g","name":"Money Talks with bestin","publisher":"bestin.capital","images":[{"height":640,"url":"https:\/\/i.scdn.co\/image\/ab6765630000ba8ab72a60a14bf99606ddf4d9b2","width":640},{"height":300,"url":"https:\/\/i.scdn.co\/image\/ab67656300005f1fb72a60a14bf99606ddf4d9b2","width":300},{"height":64,"url":"https:\/\/i.scdn.co\/image\/ab6765630000f68db72a60a14bf99606ddf4d9b2","width":64}]},{"id":"6wqBtC9OMq2mLvhDjZbqVM","name":"Jota Jota Podcast","publisher":"Joel Jota","images":[{"height":640,"url":"https:\/\/i.scdn.co\/image\/ab6765630000ba8a13eb79027efb630fe4968471","width":640},{"height":300,"url":"https:\/\/i.scdn.co\/image\/ab67656300005f1f13eb79027efb630fe4968471","width":300},{"height":64,"url":"https:\/\/i.scdn.co\/image\/ab6765630000f68d13eb79027efb630fe4968471","width":64}]},{"id":"6uwRv7GQxaJ0KmnoDuREUU","name":"Josemar Bessa","publisher":"Josemar Bessa","images":[{"height":640,"url":"https:\/\/i.scdn.co\/image\/ab6765630000ba8a17ec8f6cb93241d33fa28d62","width":640},{"height":300,"url":"https:\/\/i.scdn.co\/image\/ab67656300005f1f17ec8f6cb93241d33fa28d62","width":300},{"height":64,"url":"https:\/\/i.scdn.co\/image\/ab6765630000f68d17ec8f6cb93241d33fa28d62","width":64}]},{"id":"5RllMBgvDnTau8nnsCUdse","name":"The Best One Yet","publisher":"Nick & Jack Studios","images":[{"height":640,"url":"https:\/\/i.scdn.co\/image\/ab6765630000ba8a95ee0e49eebdd3c756ba8cfe","width":640},{"height":300,"url":"https:\/\/i.scdn.co\/image\/ab67656300005f1f95ee0e49eebdd3c756ba8cfe","width":300},{"height":64,"url":"https:\/\/i.scdn.co\/image\/ab6765630000f68d95ee0e49eebdd3c756ba8cfe","width":64}]},{"id":"22fi0RqfoBACCuQDv97wFO","name":"Invest Like the Best with Patrick O'Shaughnessy","publisher":"Colossus | Investing & Business Podcasts","images":[{"height":640,"url":"https:\/\/i.scdn.co\/image\/ab6765630000ba8aee3b7b5fbddb214f77fe8d60","width":640},{"height":300,"url":"https:\/\/i.scdn.co\/image\/ab67656300005f1fee3b7b5fbddb214f77fe8d60","width":300},{"height":64,"url":"https:\/\/i.scdn.co\/image\/ab6765630000f68dee3b7b5fbddb214f77fe8d60","width":64}]},{"id":"1QJgd5aW274UcsHAShJwSE","name":"Como Voc\u00ea Fez Isso?","publisher":"Caio Carneiro","images":[{"height":640,"url":"https:\/\/i.scdn.co\/image\/ab6765630000ba8a8e49b82a10a18cd1a142f494","width":640},{"height":300,"url":"https:\/\/i.scdn.co\/image\/ab67656300005f1f8e49b82a10a18cd1a142f494","width":300},{"height":64,"url":"https:\/\/i.scdn.co\/image\/ab6765630000f68d8e49b82a10a18cd1a142f494","width":64}]}],"tracks":[{"id":"5FZxsHWIvUsmSK1IAvm2pp","name":"Best of You","popularity":77,"images":[{"height":640,"width":640,"url":"https:\/\/i.scdn.co\/image\/ab67616d0000b2736c44679425e2695001b35d72"},{"height":300,"width":300,"url":"https:\/\/i.scdn.co\/image\/ab67616d00001e026c44679425e2695001b35d72"},{"height":64,"width":64,"url":"https:\/\/i.scdn.co\/image\/ab67616d000048516c44679425e2695001b35d72"}],"artists":[{"id":"7jy3rLJdDQY21OgRLCZ9sD","name":"Foo Fighters"}],"duration_ms":255626},{"id":"4OBZT9EnhYIV17t4pGw7ig","name":"Best Part (feat. H.E.R.)","popularity":70,"images":[{"height":640,"width":640,"url":"https:\/\/i.scdn.co\/image\/ab67616d0000b273b5d9c8de465654c20d77305c"},{"height":300,"width":300,"url":"https:\/\/i.scdn.co\/image\/ab67616d00001e02b5d9c8de465654c20d77305c"},{"height":64,"width":64,"url":"https:\/\/i.scdn.co\/image\/ab67616d00004851b5d9c8de465654c20d77305c"}],"artists":[{"id":"20wkVLutqVOYrc0kxFs7rA","name":"Daniel Caesar"},{"id":"3Y7RZ31TRPVadSFVy1o8os","name":"H.E.R."}],"duration_ms":209400},{"id":"1Q7EgiMOuwDcB0PJC6AzON","name":"Best Part (feat. H.E.R.)","popularity":86,"images":[{"height":640,"width":640,"url":"https:\/\/i.scdn.co\/image\/ab67616d0000b27305ac3e026324594a31fad7fb"},{"height":300,"width":300,"url":"https:\/\/i.scdn.co\/image\/ab67616d00001e0205ac3e026324594a31fad7fb"},{"height":64,"width":64,"url":"https:\/\/i.scdn.co\/image\/ab67616d0000485105ac3e026324594a31fad7fb"}],"artists":[{"id":"20wkVLutqVOYrc0kxFs7rA","name":"Daniel Caesar"},{"id":"3Y7RZ31TRPVadSFVy1o8os","name":"H.E.R."}],"duration_ms":209831},{"id":"0r3nMF80NSIuPIxeod4aoG","name":"Beso (Fruta Fresca)","popularity":77,"images":[{"height":640,"width":640,"url":"https:\/\/i.scdn.co\/image\/ab67616d0000b2730c1faf936b87bdf93bee8d7e"},{"height":300,"width":300,"url":"https:\/\/i.scdn.co\/image\/ab67616d00001e020c1faf936b87bdf93bee8d7e"},{"height":64,"width":64,"url":"https:\/\/i.scdn.co\/image\/ab67616d000048510c1faf936b87bdf93bee8d7e"}],"artists":[{"id":"2CnJJITnV40TB5UtCRhwIZ","name":"Wakyin"},{"id":"4vhNDa5ycK0ST968ek7kRr","name":"Carlos Vives"}],"duration_ms":197694},{"id":"5Hroj5K7vLpIG4FNCRIjbP","name":"Best Day Of My Life","popularity":83,"images":[{"height":640,"width":640,"url":"https:\/\/i.scdn.co\/image\/ab67616d0000b273cc761ba55b0e7abad4539abe"},{"height":300,"width":300,"url":"https:\/\/i.scdn.co\/image\/ab67616d00001e02cc761ba55b0e7abad4539abe"},{"height":64,"width":64,"url":"https:\/\/i.scdn.co\/image\/ab67616d00004851cc761ba55b0e7abad4539abe"}],"artists":[{"id":"0MlOPi3zIDMVrfA9R04Fe3","name":"American Authors"}],"duration_ms":194240},{"id":"0hWzBcYtmwsL1TwByzjiUG","name":"Boy Besta","popularity":75,"images":[{"height":640,"width":640,"url":"https:\/\/i.scdn.co\/image\/ab67616d0000b273320f4a08913b939a8637c301"},{"height":300,"width":300,"url":"https:\/\/i.scdn.co\/image\/ab67616d00001e02320f4a08913b939a8637c301"},{"height":64,"width":64,"url":"https:\/\/i.scdn.co\/image\/ab67616d00004851320f4a08913b939a8637c301"}],"artists":[{"id":"6XFc29m1ptfUNmaa1UTuBT","name":"MC Jo\u00e3ozinho VT"},{"id":"4LHTgACY32k94VDjenF0nP","name":"Mc Neg\u00e3o Original"},{"id":"6aoGgTKGqtsjj48ymcNs4Z","name":"MC Tuto"},{"id":"5InVWl8IZB8zFAoNa5roKm","name":"Mc Kako"},{"id":"75i9GaW2MJUgt4BkdUnuUY","name":"MC Ryan SP"},{"id":"3InqACcEpcWEHMTiQcwB4Y","name":"Matheuszin DJ"}],"duration_ms":424615},{"id":"5T7ZFtCcOgkpjxcuaeZbw0","name":"Best Song Ever","popularity":79,"images":[{"height":640,"width":640,"url":"https:\/\/i.scdn.co\/image\/ab67616d0000b2732f76b797c382bedcafdf45e1"},{"height":300,"width":300,"url":"https:\/\/i.scdn.co\/image\/ab67616d00001e022f76b797c382bedcafdf45e1"},{"height":64,"width":64,"url":"https:\/\/i.scdn.co\/image\/ab67616d000048512f76b797c382bedcafdf45e1"}],"artists":[{"id":"4AK6F7OLvEQ5QYCBNiQWHq","name":"One Direction"}],"duration_ms":200106},{"id":"3jHdKaLCkuNEkWcLVmQPCX","name":"BEST INTEREST","popularity":83,"images":[{"height":640,"width":640,"url":"https:\/\/i.scdn.co\/image\/ab67616d0000b273ab8995f18dc3dd9f34a6acd4"},{"height":300,"width":300,"url":"https:\/\/i.scdn.co\/image\/ab67616d00001e02ab8995f18dc3dd9f34a6acd4"},{"height":64,"width":64,"url":"https:\/\/i.scdn.co\/image\/ab67616d00004851ab8995f18dc3dd9f34a6acd4"}],"artists":[{"id":"4V8LLVI7PbaPR0K2TGSxFF","name":"Tyler, The Creator"}],"duration_ms":127921},{"id":"3rPtS4nfpy7PsARctAWpzd","name":"Best Friend","popularity":77,"images":[{"height":640,"width":640,"url":"https:\/\/i.scdn.co\/image\/ab67616d0000b273ff874602e13e9181c26e5f01"},{"height":300,"width":300,"url":"https:\/\/i.scdn.co\/image\/ab67616d00001e02ff874602e13e9181c26e5f01"},{"height":64,"width":64,"url":"https:\/\/i.scdn.co\/image\/ab67616d00004851ff874602e13e9181c26e5f01"}],"artists":[{"id":"7pbDxGE6nQSZVfiFdq9lOL","name":"Rex Orange County"}],"duration_ms":262231},{"id":"6XEiHPKRqobg7jymVQI5lj","name":"Bestasexual - Ao Vivo","popularity":22,"images":[{"height":640,"width":640,"url":"https:\/\/i.scdn.co\/image\/ab67616d0000b273db11f78c4bc296f5a77d7c33"},{"height":300,"width":300,"url":"https:\/\/i.scdn.co\/image\/ab67616d00001e02db11f78c4bc296f5a77d7c33"},{"height":64,"width":64,"url":"https:\/\/i.scdn.co\/image\/ab67616d00004851db11f78c4bc296f5a77d7c33"}],"artists":[{"id":"3k68C6mNMJL6OaAdWeW2ZF","name":"Diego & Victor Hugo"}],"duration_ms":168118}],"best_result":{"type":"artist","id":"03r4iKL2g2442PT9n2UKsx","name":"Beastie Boys","popularity":71,"images":[{"url":"https:\/\/i.scdn.co\/image\/705bcd56dc5dbf9ebc578a3ba8094e6d622862c2","height":771,"width":1000},{"url":"https:\/\/i.scdn.co\/image\/060ef251f0e12353057c36fe94724b688b963dac","height":494,"width":640},{"url":"https:\/\/i.scdn.co\/image\/eb9a69f247e84b9e9ce8b03f1ab5cca399b49cbc","height":154,"width":200},{"url":"https:\/\/i.scdn.co\/image\/b6fafee2c4c169dadf039c2066ab77beb4c82b3e","height":49,"width":64}],"artists":[{"id":"03r4iKL2g2442PT9n2UKsx","name":"Beastie Boys"}]}}