{"artists":[{"id":"2ye2Wgw4gimLv2eAKyk1NB","name":"Metallica","popularity":84,"images":[{"url":"https:\/\/i.scdn.co\/image\/ab6761610000e5eb69ca98dd3083f1082d740e44","height":640,"width":640},{"url":"https:\/\/i.scdn.co\/image\/ab6761610000517469ca98dd3083f1082d740e44","height":320,"width":320},{"url":"https:\/\/i.scdn.co\/image\/ab6761610000f17869ca98dd3083f1082d740e44","height":160,"width":160}]},{"id":"711MCceyCBcFnzjGY4Q7Un","name":"AC\/DC","popularity":83,"images":[{"url":"https:\/\/i.scdn.co\/image\/ab6761610000e5ebc4c77549095c86acb4e77b37","height":640,"width":640},{"url":"https:\/\/i.scdn.co\/image\/ab67616100005174c4c77549095c86acb4e77b37","height":320,"width":320},{"url":"https:\/\/i.scdn.co\/image\/ab6761610000f178c4c77549095c86acb4e77b37","height":160,"width":160}]},{"id":"05fG473iIaoy82BF1aGhL8","name":"Slipknot","popularity":81,"images":[{"url":"https:\/\/i.scdn.co\/image\/ab6761610000e5ebd0cdb283a7384a0edb665182","height":640,"width":640},{"url":"https:\/\/i.scdn.co\/image\/ab67616100005174d0cdb283a7384a0edb665182","height":320,"width":320},{"url":"https:\/\/i.scdn.co\/image\/ab6761610000f178d0cdb283a7384a0edb665182","height":160,"width":160}]},{"id":"3qm84nBOXUEQ2vnTfUTTFC","name":"Guns N' Roses","popularity":82,"images":[{"url":"https:\/\/i.scdn.co\/image\/ab6761610000e5eb50defaf9fc059a1efc541f4c","height":640,"width":640},{"url":"https:\/\/i.scdn.co\/image\/ab6761610000517450defaf9fc059a1efc541f4c","height":320,"width":320},{"url":"https:\/\/i.scdn.co\/image\/ab6761610000f17850defaf9fc059a1efc541f4c","height":160,"width":160}]},{"id":"6mdiAmATAx73kdxrNrnlao","name":"Iron Maiden","popularity":74,"images":[{"url":"https:\/\/i.scdn.co\/image\/ab6761610000e5ebf9978ad4808f6f2723124d19","height":640,"width":640},{"url":"https:\/\/i.scdn.co\/image\/ab67616100005174f9978ad4808f6f2723124d19","height":320,"width":320},{"url":"https:\/\/i.scdn.co\/image\/ab6761610000f178f9978ad4808f6f2723124d19","height":160,"width":160}]},{"id":"5eAWCfyUhZtHHtBdNk56l1","name":"System Of A Down","popularity":83,"images":[{"url":"https:\/\/i.scdn.co\/image\/ab6761610000e5eb60063d3451ade8f9fab397c2","height":640,"width":640},{"url":"https:\/\/i.scdn.co\/image\/ab6761610000517460063d3451ade8f9fab397c2","height":320,"width":320},{"url":"https:\/\/i.scdn.co\/image\/ab6761610000f17860063d3451ade8f9fab397c2","height":160,"width":160}]},{"id":"5M52tdBnJaKSvOpJGz8mfZ","name":"Black Sabbath","popularity":75,"images":[{"url":"https:\/\/i.scdn.co\/image\/ab6761610000e5eb4870cd833ebe1092601820c3","height":640,"width":640},{"url":"https:\/\/i.scdn.co\/image\/ab676161000051744870cd833ebe1092601820c3","height":320,"width":320},{"url":"https:\/\/i.scdn.co\/image\/ab6761610000f1784870cd833ebe1092601820c3","height":160,"width":160}]},{"id":"3mmIYQi9wrQnA9mRPXHAWg","name":"Deus Metallicus","popularity":31,"images":[{"url":"https:\/\/i.scdn.co\/image\/ab6761610000e5eb9c7d471d7a87768b51150318","height":640,"width":640},{"url":"https:\/\/i.scdn.co\/image\/ab676161000051749c7d471d7a87768b51150318","height":320,"width":320},{"url":"https:\/\/i.scdn.co\/image\/ab6761610000f1789c7d471d7a87768b51150318","height":160,"width":160}]},{"id":"0exvkfkATkqWOJgugTjJhP","name":"Metal Church","popularity":43,"images":[{"url":"https:\/\/i.scdn.co\/image\/ab6772690000c46c3ca4ece56e5fd4324ff7bd36","height":1000,"width":1000},{"url":"https:\/\/i.scdn.co\/image\/ab6772690000dd223ca4ece56e5fd4324ff7bd36","height":640,"width":640},{"url":"https:\/\/i.scdn.co\/image\/ab6772690000bac33ca4ece56e5fd4324ff7bd36","height":200,"width":200},{"url":"https:\/\/i.scdn.co\/image\/ab67726900008f743ca4ece56e5fd4324ff7bd36","height":64,"width":64}]},{"id":"7u12AuhJ5AaJIgZAZe0US8","name":"Metalocalypse: Dethklok","popularity":55,"images":[{"url":"https:\/\/i.scdn.co\/image\/ab67616d0000b273533644c194069d80a08109cf","height":640,"width":640},{"url":"https:\/\/i.scdn.co\/image\/ab67616d00001e025cee455d46a98b46e1c7dd73","height":300,"width":300},{"url":"https:\/\/i.scdn.co\/image\/ab67616d00004851533644c194069d80a08109cf","height":64,"width":64}]}],"albums":[{"id":"1aGapZGHBovnmhwqVNI6JZ","name":"Kill 'Em All (Remastered)","images":[{"height":640,"url":"https:\/\/i.scdn.co\/image\/ab67616d0000b273d30fcf6340831edbafb45e38","width":640},{"height":300,"url":"https:\/\/i.scdn.co\/image\/ab67616d00001e02d30fcf6340831edbafb45e38","width":300},{"height":64,"url":"https:\/\/i.scdn.co\/image\/ab67616d00004851d30fcf6340831edbafb45e38","width":64}],"artists":[{"id":"2ye2Wgw4gimLv2eAKyk1NB","name":"Metallica"}]},{"id":"05DePtm7oQMdL3Uzw2Jmsc","name":"Ride The Lightning (Remastered)","images":[{"height":640,"url":"https:\/\/i.scdn.co\/image\/ab67616d0000b2739ad3e9959f48d513886b8933","width":640},{"height":300,"url":"https:\/\/i.scdn.co\/image\/ab67616d00001e029ad3e9959f48d513886b8933","width":300},{"height":64,"url":"https:\/\/i.scdn.co\/image\/ab67616d000048519ad3e9959f48d513886b8933","width":64}],"artists":[{"id":"2ye2Wgw4gimLv2eAKyk1NB","name":"Metallica"}]},{"id":"6jZ1z25PyF4Yd3kHxt9rl1","name":"\u2026And Justice for All (Remastered)","images":[{"height":640,"url":"https:\/\/i.scdn.co\/image\/ab67616d0000b273fe896727e3db1027ed72d885","width":640},{"height":300,"url":"https:\/\/i.scdn.co\/image\/ab67616d00001e02fe896727e3db1027ed72d885","width":300},{"height":64,"url":"https:\/\/i.scdn.co\/image\/ab67616d00004851fe896727e3db1027ed72d885","width":64}],"artists":[{"id":"2ye2Wgw4gimLv2eAKyk1NB","name":"Metallica"}]},{"id":"2Lq2qX3hYhiuPckC8Flj21","name":"Master Of Puppets (Remastered)","images":[{"height":640,"url":"https:\/\/i.scdn.co\/image\/ab67616d0000b273668e3aca3167e6e569a9aa20","width":640},{"height":300,"url":"https:\/\/i.scdn.co\/image\/ab67616d00001e02668e3aca3167e6e569a9aa20","width":300},{"height":64,"url":"https:\/\/i.scdn.co\/image\/ab67616d00004851668e3aca3167e6e569a9aa20","width":64}],"artists":[{"id":"2ye2Wgw4gimLv2eAKyk1NB","name":"Metallica"}]},{"id":"3dck2tBxGfxj9m3CguDgjb","name":"Metallica (Remastered 2021)","images":[{"height":640,"url":"https:\/\/i.scdn.co\/image\/ab67616d0000b27376c60d2128c8e4649b85f2b2","width":640},{"height":300,"url":"https:\/\/i.scdn.co\/image\/ab67616d00001e0276c60d2128c8e4649b85f2b2","width":300},{"height":64,"url":"https:\/\/i.scdn.co\/image\/ab67616d0000485176c60d2128c8e4649b85f2b2","width":64}],"artists":[{"id":"2ye2Wgw4gimLv2eAKyk1NB","name":"Metallica"}]},{"id":"0vshXZYhBkbIoqxyC2fXcF","name":"Garage Inc.","images":[{"height":640,"url":"https:\/\/i.scdn.co\/image\/ab67616d0000b27375e6375e11550746705a9645","width":640},{"height":300,"url":"https:\/\/i.scdn.co\/image\/ab67616d00001e0275e6375e11550746705a9645","width":300},{"height":64,"url":"https:\/\/i.scdn.co\/image\/ab67616d0000485175e6375e11550746705a9645","width":64}],"artists":[{"id":"2ye2Wgw4gimLv2eAKyk1NB","name":"Metallica"}]},{"id":"0Ip2GlQPoAIgdkqCO2YkMa","name":"Reload","images":[{"height":640,"url":"https:\/\/i.scdn.co\/image\/ab67616d0000b27306cb74d39d123ebe1b3c6631","width":640},{"height":300,"url":"https:\/\/i.scdn.co\/image\/ab67616d00001e0206cb74d39d123ebe1b3c6631","width":300},{"height":64,"url":"https:\/\/i.scdn.co\/image\/ab67616d0000485106cb74d39d123ebe1b3c6631","width":64}],"artists":[{"id":"2ye2Wgw4gimLv2eAKyk1NB","name":"Metallica"}]},{"id":"7h5xn0Olvx2p0eQcSt1Osy","name":"Metallica (Remastered Deluxe Box Set)","images":[{"height":640,"url":"https:\/\/i.scdn.co\/image\/ab67616d0000b273c1a13209dfe146aef3296e34","width":640},{"height":300,"url":"https:\/\/i.scdn.co\/image\/ab67616d00001e02c1a13209dfe146aef3296e34","width":300},{"height":64,"url":"https:\/\/i.scdn.co\/image\/ab67616d00004851c1a13209dfe146aef3296e34","width":64}],"artists":[{"id":"2ye2Wgw4gimLv2eAKyk1NB","name":"Metallica"}]},{"id":"4K5E5mWQbECn9aThu6Xnkx","name":"Ride The Lightning (Deluxe \/ Remastered)","images":[{"height":640,"url":"https:\/\/i.scdn.co\/image\/ab67616d0000b27396a926d07aea417327ea024a","width":640},{"height":300,"url":"https:\/\/i.scdn.co\/image\/ab67616d00001e0296a926d07aea417327ea024a","width":300},{"height":64,"url":"https:\/\/i.scdn.co\/image\/ab67616d0000485196a926d07aea417327ea024a","width":64}],"artists":[{"id":"2ye2Wgw4gimLv2eAKyk1NB","name":"Metallica"}]},{"id":"2iq8AWMGVYu3yM1sitL1Iu","name":"Metallic Menace + Espionoir (Gold Edition Soundtracks)","images":[{"height":640,"url":"https:\/\/i.scdn.co\/image\/ab67616d0000b273a88910b47fdc758bce2a44b1","width":640},{"height":300,"url":"https:\/\/i.scdn.co\/image\/ab67616d00001e02a88910b47fdc758bce2a44b1","width":300},{"height":64,"url":"https:\/\/i.scdn.co\/image\/ab67616d00004851a88910b47fdc758bce2a44b1","width":64}],"artists":[{"id":"4blGvgFNtOZdyEDeATXN7r","name":"Sabian Roberts"}]}],"playlists":[{"id":"4no4zedgRHSygeMmAP9prD","name":"Metallica","images":[{"height":640,"url":"https:\/\/mosaic.scdn.co\/640\/ab67616d00001e02668e3aca3167e6e569a9aa20ab67616d00001e0276c60d2128c8e4649b85f2b2ab67616d00001e029ad3e9959f48d513886b8933ab67616d00001e02c1a13209dfe146aef3296e34","width":640},{"height":300,"url":"https:\/\/mosaic.scdn.co\/300\/ab67616d00001e02668e3aca3167e6e569a9aa20ab67616d00001e0276c60d2128c8e4649b85f2b2ab67616d00001e029ad3e9959f48d513886b8933ab67616d00001e02c1a13209dfe146aef3296e34","width":300},{"height":60,"url":"https:\/\/mosaic.scdn.co\/60\/ab67616d00001e02668e3aca3167e6e569a9aa20ab67616d00001e0276c60d2128c8e4649b85f2b2ab67616d00001e029ad3e9959f48d513886b8933ab67616d00001e02c1a13209dfe146aef3296e34","width":60}]},{"id":"5qzVsC4JNzrgRfyOntjJ3H","name":"Metallica - S\u00f3 as Melhores","images":[{"height":null,"url":"https:\/\/image-cdn-ak.spotifycdn.com\/image\/ab67706c0000d72cec9e55d85944df8e93c8cbd2","width":null}]},{"id":"34qQU9UMJ1cLmteEMETQEd","name":"Metallica: S\u00d3 AS MELHORES","images":[{"height":640,"url":"https:\/\/mosaic.scdn.co\/640\/ab67616d00001e02668e3aca3167e6e569a9aa20ab67616d00001e029ad3e9959f48d513886b8933ab67616d00001e02d30fcf6340831edbafb45e38ab67616d00001e02fe896727e3db1027ed72d885","width":640},{"height":300,"url":"https:\/\/mosaic.scdn.co\/300\/ab67616d00001e02668e3aca3167e6e569a9aa20ab67616d00001e029ad3e9959f48d513886b8933ab67616d00001e02d30fcf6340831edbafb45e38ab67616d00001e02fe896727e3db1027ed72d885","width":300},{"height":60,"url":"https:\/\/mosaic.scdn.co\/60\/ab67616d00001e02668e3aca3167e6e569a9aa20ab67616d00001e029ad3e9959f48d513886b8933ab67616d00001e02d30fcf6340831edbafb45e38ab67616d00001e02fe896727e3db1027ed72d885","width":60}]},{"id":"6WNmeutRfJLFVXtuG2ObK7","name":"METAL PRA TREINAR NA FOR\u00c7A DO \u00d3DIO\ud83e\udd18\ud83d\udd25","images":[{"height":null,"url":"https:\/\/image-cdn-ak.spotifycdn.com\/image\/ab67706c0000da84f82958c325b7334de1ae93a1","width":null}]},{"id":"38TKXlDP8ASiueQZbcJRmT","name":"Met\u00e1lica - Nothing Else Matters","images":[{"height":null,"url":"https:\/\/i.scdn.co\/image\/ab67616d00001e02c1a13209dfe146aef3296e34","width":null}]},{"id":"5JJXmCsIJb0FN4dJ5D7ZxN","name":"AC\/DC - As Melhores | Highway to Hell","images":[{"height":null,"url":"https:\/\/image-cdn-ak.spotifycdn.com\/image\/ab67706c0000da84f4dcbb70e5b7b56228adfbec","width":null}]},{"id":"4BWdcaxeNL1kmVjGEj3vxh","name":"Rock Anos 90 e 2000 Internacional. As melhores!","images":[{"height":null,"url":"https:\/\/image-cdn-ak.spotifycdn.com\/image\/ab67706c0000d72c5b9d00469d5206b19f346676","width":null}]}],"podcasts":[{"id":"14jalMOh1Jr77eTRUdN6X9","name":"Intelig\u00eancia Ltda.","publisher":"Rog\u00e9rio Vilela","images":[{"height":640,"url":"https:\/\/i.scdn.co\/image\/ab6765630000ba8a7fbf5d3b676ba83b4a1867b3","width":640},{"height":300,"url":"https:\/\/i.scdn.co\/image\/ab67656300005f1f7fbf5d3b676ba83b4a1867b3","width":300},{"height":64,"url":"https:\/\/i.scdn.co\/image\/ab6765630000f68d7fbf5d3b676ba83b4a1867b3","width":64}]},{"id":"3V5LBozjo4vNg2oJoA4Wb2","name":"Flow Podcast","publisher":"Grupo Flow","images":[{"height":640,"url":"https:\/\/i.scdn.co\/image\/ab6765630000ba8a28c5bbf0560908592d537e3b","width":640},{"height":300,"url":"https:\/\/i.scdn.co\/image\/ab67656300005f1f28c5bbf0560908592d537e3b","width":300},{"height":64,"url":"https:\/\/i.scdn.co\/image\/ab6765630000f68d28c5bbf0560908592d537e3b","width":64}]},{"id":"6EJUwYDC2vdgdZ28sghbh5","name":"TICARACATICAST","publisher":"TICARACATICAST","images":[{"height":640,"url":"https:\/\/i.scdn.co\/image\/ab6765630000ba8abe52b62cd2456fdd6712a02e","width":640},{"height":300,"url":"https:\/\/i.scdn.co\/image\/ab67656300005f1fbe52b62cd2456fdd6712a02e","width":300},{"height":64,"url":"https:\/\/i.scdn.co\/image\/ab6765630000f68dbe52b62cd2456fdd6712a02e","width":64}]},{"id":"22Wgt4ASeaw8mmoqAWNUn1","name":"NerdCast","publisher":"Jovem Nerd","images":[{"height":640,"url":"https:\/\/i.scdn.co\/image\/ab6765630000ba8af98403d2282f57df937c5fb5","width":640},{"height":300,"url":"https:\/\/i.scdn.co\/image\/ab67656300005f1ff98403d2282f57df937c5fb5","width":300},{"height":64,"url":"https:\/\/i.scdn.co\/image\/ab6765630000f68df98403d2282f57df937c5fb5","width":64}]},{"id":"2gCj9YG9tjMexhS4pIlRHo","name":"PrimoCast","publisher":"Grupo Primo ","images":[{"height":640,"url":"https:\/\/i.scdn.co\/image\/ab6765630000ba8a83496c5984ded6393ea0f1b4","width":640},{"height":300,"url":"https:\/\/i.scdn.co\/image\/ab67656300005f1f83496c5984ded6393ea0f1b4","width":300},{"height":64,"url":"https:\/\/i.scdn.co\/image\/ab6765630000f68d83496c5984ded6393ea0f1b4","width":64}]},{"id":"7D8wv41RwnqtwRRSvul85a","name":"METAL UP YOUR PODCAST - All Things Metallica","publisher":"Clint Wells","images":[{"height":640,"url":"https:\/\/i.scdn.co\/image\/ab6765630000ba8a5cac5c20142764be1270e21a","width":640},{"height":300,"url":"https:\/\/i.scdn.co\/image\/ab67656300005f1f5cac5c20142764be1270e21a","width":300},{"height":64,"url":"https:\/\/i.scdn.co\/image\/ab6765630000f68d5cac5c20142764be1270e21a","width":64}]},{"id":"3lQ1tOcsLQsgBViuttVzAX","name":"The Metallica Report","publisher":"Metallica & Pantheon Media","images":[{"height":640,"url":"https:\/\/i.scdn.co\/image\/ab6765630000ba8a20a96b30c3585ea0e97f39ad","width":640},{"height":300,"url":"https:\/\/i.scdn.co\/image\/ab67656300005f1f20a96b30c3585ea0e97f39ad","width":300},{"height":64,"url":"https:\/\/i.scdn.co\/image\/ab6765630000f68d20a96b30c3585ea0e97f39ad","width":64}]},{"id":"1LnPMFQyBHDpLNOE8VWVL1","name":"The Metallica Podcast: Volume 1 \u2014 The Black Album","publisher":"Metallica & Amazon","images":[{"height":640,"url":"https:\/\/i.scdn.co\/image\/ab6765630000ba8a31bd6b7a72827d4e9122b8ef","width":640},{"height":300,"url":"https:\/\/i.scdn.co\/image\/ab67656300005f1f31bd6b7a72827d4e9122b8ef","width":300},{"height":64,"url":"https:\/\/i.scdn.co\/image\/ab6765630000f68d31bd6b7a72827d4e9122b8ef","width":64}]},{"id":"26GYVcRiP1IBawMREzZSEa","name":"Nothing Else Matters! Der Metallica-Podcast bei RADIO BOB!","publisher":"RADIO BOB!","images":[{"height":640,"url":"https:\/\/i.scdn.co\/image\/ab6765630000ba8a2fb33f98bd8038ba76ab5649","width":640},{"height":300,"url":"https:\/\/i.scdn.co\/image\/ab67656300005f1f2fb33f98bd8038ba76ab5649","width":300},{"height":64,"url":"https:\/\/i.scdn.co\/image\/ab6765630000f68d2fb33f98bd8038ba76ab5649","width":64}]},{"id":"765HkmRaLMymQ1H30OFeMT","name":"Metallichat.","publisher":"metallichatpod@gmail.com","images":[{"height":640,"url":"https:\/\/i.scdn.co\/image\/ab6765630000ba8abca5ef427e99e844780b604b","width":640},{"height":300,"url":"https:\/\/i.scdn.co\/image\/ab67656300005f1fbca5ef427e99e844780b604b","width":300},{"height":64,"url":"https:\/\/i.scdn.co\/image\/ab6765630000f68dbca5ef427e99e844780b604b","width":64}]}],"tracks":[{"id":"2dXsILW8gzkosqleHAvl0v","name":"For Whom The Bell Tolls - Remastered","popularity":68,"images":[{"height":640,"width":640,"url":"https:\/\/i.scdn.co\/image\/ab67616d0000b2739ad3e9959f48d513886b8933"},{"height":300,"width":300,"url":"https:\/\/i.scdn.co\/image\/ab67616d00001e029ad3e9959f48d513886b8933"},{"height":64,"width":64,"url":"https:\/\/i.scdn.co\/image\/ab67616d000048519ad3e9959f48d513886b8933"}],"artists":[{"id":"2ye2Wgw4gimLv2eAKyk1NB","name":"Metallica"}],"duration_ms":309973},{"id":"02xhLoVqpGmOqvolgrwM8w","name":"One","popularity":72,"images":[{"height":640,"width":640,"url":"https:\/\/i.scdn.co\/image\/ab67616d0000b273fe896727e3db1027ed72d885"},{"height":300,"width":300,"url":"https:\/\/i.scdn.co\/image\/ab67616d00001e02fe896727e3db1027ed72d885"},{"height":64,"width":64,"url":"https:\/\/i.scdn.co\/image\/ab67616d00004851fe896727e3db1027ed72d885"}],"artists":[{"id":"2ye2Wgw4gimLv2eAKyk1NB","name":"Metallica"}],"duration_ms":446145},{"id":"5nekfiTN45vlxG0eNJQQye","name":"Fade To Black - Remastered","popularity":71,"images":[{"height":640,"width":640,"url":"https:\/\/i.scdn.co\/image\/ab67616d0000b27396a926d07aea417327ea024a"},{"height":300,"width":300,"url":"https:\/\/i.scdn.co\/image\/ab67616d00001e0296a926d07aea417327ea024a"},{"height":64,"width":64,"url":"https:\/\/i.scdn.co\/image\/ab67616d0000485196a926d07aea417327ea024a"}],"artists":[{"id":"2ye2Wgw4gimLv2eAKyk1NB","name":"Metallica"}],"duration_ms":417226},{"id":"6nswV1Lz3OZkaiCJfmVUOa","name":"The Unforgiven II","popularity":70,"images":[{"height":640,"width":640,"url":"https:\/\/i.scdn.co\/image\/ab67616d0000b27306cb74d39d123ebe1b3c6631"},{"height":300,"width":300,"url":"https:\/\/i.scdn.co\/image\/ab67616d00001e0206cb74d39d123ebe1b3c6631"},{"height":64,"width":64,"url":"https:\/\/i.scdn.co\/image\/ab67616d0000485106cb74d39d123ebe1b3c6631"}],"artists":[{"id":"2ye2Wgw4gimLv2eAKyk1NB","name":"Metallica"}],"duration_ms":396440},{"id":"5JAnXx5BBES4FEf4d4t4CC","name":"St. Anger","popularity":62,"images":[{"height":640,"width":640,"url":"https:\/\/i.scdn.co\/image\/ab67616d0000b273ee5869b2880109918fc47199"},{"height":300,"width":300,"url":"https:\/\/i.scdn.co\/image\/ab67616d00001e02ee5869b2880109918fc47199"},{"height":64,"width":64,"url":"https:\/\/i.scdn.co\/image\/ab67616d00004851ee5869b2880109918fc47199"}],"artists":[{"id":"2ye2Wgw4gimLv2eAKyk1NB","name":"Metallica"}],"duration_ms":441132},{"id":"3DwQ7AH3xGD9h65ezslm6q","name":"Enter Sandman - Remastered 2021","popularity":80,"images":[{"height":640,"width":640,"url":"https:\/\/i.scdn.co\/image\/ab67616d0000b273c1a13209dfe146aef3296e34"},{"height":300,"width":300,"url":"https:\/\/i.scdn.co\/image\/ab67616d00001e02c1a13209dfe146aef3296e34"},{"height":64,"width":64,"url":"https:\/\/i.scdn.co\/image\/ab67616d00004851c1a13209dfe146aef3296e34"}],"artists":[{"id":"2ye2Wgw4gimLv2eAKyk1NB","name":"Metallica"}],"duration_ms":331560},{"id":"2O7UGwJPVlix15Wn4sa5vw","name":"Ride The Lightning - Remastered","popularity":65,"images":[{"height":640,"width":640,"url":"https:\/\/i.scdn.co\/image\/ab67616d0000b27396a926d07aea417327ea024a"},{"height":300,"width":300,"url":"https:\/\/i.scdn.co\/image\/ab67616d00001e0296a926d07aea417327ea024a"},{"height":64,"width":64,"url":"https:\/\/i.scdn.co\/image\/ab67616d0000485196a926d07aea417327ea024a"}],"artists":[{"id":"2ye2Wgw4gimLv2eAKyk1NB","name":"Metallica"}],"duration_ms":396986},{"id":"4d50VgYqfw1Rd0knRRL3qv","name":"Ride The Lightning - Remastered","popularity":55,"images":[{"height":640,"width":640,"url":"https:\/\/i.scdn.co\/image\/ab67616d0000b2739ad3e9959f48d513886b8933"},{"height":300,"width":300,"url":"https:\/\/i.scdn.co\/image\/ab67616d00001e029ad3e9959f48d513886b8933"},{"height":64,"width":64,"url":"https:\/\/i.scdn.co\/image\/ab67616d000048519ad3e9959f48d513886b8933"}],"artists":[{"id":"2ye2Wgw4gimLv2eAKyk1NB","name":"Metallica"}],"duration_ms":396986},{"id":"5BH2yWVpiRE91Kp1lI5IWH","name":"Nothing Else Matters - Live In Rio de Janeiro, Brazil - September 19th, 2015","popularity":39,"images":[{"height":640,"width":640,"url":"https:\/\/i.scdn.co\/image\/ab67616d0000b27395958b5d219f1b328f083e08"},{"height":300,"width":300,"url":"https:\/\/i.scdn.co\/image\/ab67616d00001e0295958b5d219f1b328f083e08"},{"height":64,"width":64,"url":"https:\/\/i.scdn.co\/image\/ab67616d0000485195958b5d219f1b328f083e08"}],"artists":[{"id":"2ye2Wgw4gimLv2eAKyk1NB","name":"Metallica"}],"duration_ms":367362},{"id":"6QAsrXPnMSXIbV0yEJHlEX","name":"Nothing Else Matters - Remastered 2021","popularity":78,"images":[{"height":640,"width":640,"url":"https:\/\/i.scdn.co\/image\/ab67616d0000b273c1a13209dfe146aef3296e34"},{"height":300,"width":300,"url":"https:\/\/i.scdn.co\/image\/ab67616d00001e02c1a13209dfe146aef3296e34"},{"height":64,"width":64,"url":"https:\/\/i.scdn.co\/image\/ab67616d00004851c1a13209dfe146aef3296e34"}],"artists":[{"id":"2ye2Wgw4gimLv2eAKyk1NB","name":"Metallica"}],"duration_ms":388733}],"best_result":{"type":"artist","id":"2ye2Wgw4gimLv2eAKyk1NB","name":"Metallica","popularity":84,"images":[{"url":"https:\/\/i.scdn.co\/image\/ab6761610000e5eb69ca98dd3083f1082d740e44","height":640,"width":640},{"url":"https:\/\/i.scdn.co\/image\/ab6761610000517469ca98dd3083f1082d740e44","height":320,"width":320},{"url":"https:\/\/i.scdn.co\/image\/ab6761610000f17869ca98dd3083f1082d740e44","height":160,"width":160}],"artists":[{"id":"2ye2Wgw4gimLv2eAKyk1NB","name":"Metallica"}]}}