{"artists":[{"id":"1w5Kfo2jwwIPruYS2UWh56","name":"Pearl Jam","popularity":77,"images":[{"url":"https:\/\/i.scdn.co\/image\/ab6761610000e5ebe431fb8ba17cdee73e4ce08a","height":640,"width":640},{"url":"https:\/\/i.scdn.co\/image\/ab67616100005174e431fb8ba17cdee73e4ce08a","height":320,"width":320},{"url":"https:\/\/i.scdn.co\/image\/ab6761610000f178e431fb8ba17cdee73e4ce08a","height":160,"width":160}]},{"id":"2ziB7fzrXBoh1HUPS6sVFn","name":"Audioslave","popularity":73,"images":[{"url":"https:\/\/i.scdn.co\/image\/ab6761610000e5eb5a865295befda9e060a72cb0","height":640,"width":640},{"url":"https:\/\/i.scdn.co\/image\/ab676161000051745a865295befda9e060a72cb0","height":320,"width":320},{"url":"https:\/\/i.scdn.co\/image\/ab6761610000f1785a865295befda9e060a72cb0","height":160,"width":160}]},{"id":"5xUf6j4upBrXZPg6AI4MRK","name":"Soundgarden","popularity":71,"images":[{"url":"https:\/\/i.scdn.co\/image\/ab6761610000e5ebafa254b2a224584485286526","height":640,"width":640},{"url":"https:\/\/i.scdn.co\/image\/ab67616100005174afa254b2a224584485286526","height":320,"width":320},{"url":"https:\/\/i.scdn.co\/image\/ab6761610000f178afa254b2a224584485286526","height":160,"width":160}]},{"id":"2hEczYx7XavJ02BNPaJmTQ","name":"Pearl Jam Piano Tribute","popularity":3,"images":[]},{"id":"1on7ZQ2pvgeQF4vmIA09x5","name":"Charlie Brown Jr.","popularity":77,"images":[{"url":"https:\/\/i.scdn.co\/image\/ab6761610000e5eb67bc48f32d1cc16497865361","height":640,"width":640},{"url":"https:\/\/i.scdn.co\/image\/ab6761610000517467bc48f32d1cc16497865361","height":320,"width":320},{"url":"https:\/\/i.scdn.co\/image\/ab6761610000f17867bc48f32d1cc16497865361","height":160,"width":160}]},{"id":"5PRYoMea8zz16Jhb3WynkL","name":"Pearl James","popularity":19,"images":[{"url":"https:\/\/i.scdn.co\/image\/ab67616d0000b2731ed5cd9016bc0813c179e3c6","height":640,"width":640},{"url":"https:\/\/i.scdn.co\/image\/ab67616d00001e021ed5cd9016bc0813c179e3c6","height":300,"width":300},{"url":"https:\/\/i.scdn.co\/image\/ab67616d000048511ed5cd9016bc0813c179e3c6","height":64,"width":64}]},{"id":"2dmQ0vMD3THLMcz7DsvfaT","name":"Pitty","popularity":65,"images":[{"url":"https:\/\/i.scdn.co\/image\/ab6761610000e5eb1183488d72f571f4b079c5d5","height":640,"width":640},{"url":"https:\/\/i.scdn.co\/image\/ab676161000051741183488d72f571f4b079c5d5","height":320,"width":320},{"url":"https:\/\/i.scdn.co\/image\/ab6761610000f1781183488d72f571f4b079c5d5","height":160,"width":160}]},{"id":"4C4kpaAdp6aKSkguw40SsU","name":"Skank","popularity":68,"images":[{"url":"https:\/\/i.scdn.co\/image\/ab6761610000e5eb2b61503716c9cbb86f6a0658","height":640,"width":640},{"url":"https:\/\/i.scdn.co\/image\/ab676161000051742b61503716c9cbb86f6a0658","height":320,"width":320},{"url":"https:\/\/i.scdn.co\/image\/ab6761610000f1782b61503716c9cbb86f6a0658","height":160,"width":160}]},{"id":"6UGfKivLtHEJnrNdPcZHZh","name":"Pearl Melendez","popularity":44,"images":[{"url":"https:\/\/i.scdn.co\/image\/ab6761610000e5ebfaebe11d74a2a3c968793075","height":640,"width":640},{"url":"https:\/\/i.scdn.co\/image\/ab67616100005174faebe11d74a2a3c968793075","height":320,"width":320},{"url":"https:\/\/i.scdn.co\/image\/ab6761610000f178faebe11d74a2a3c968793075","height":160,"width":160}]},{"id":"4L8v7LCc2BtljMWBEvSgCh","name":"Pearl Ramos","popularity":18,"images":[{"url":"https:\/\/i.scdn.co\/image\/ab6761610000e5eb1ae399175eae76e631eb1816","height":640,"width":640},{"url":"https:\/\/i.scdn.co\/image\/ab676161000051741ae399175eae76e631eb1816","height":320,"width":320},{"url":"https:\/\/i.scdn.co\/image\/ab6761610000f1781ae399175eae76e631eb1816","height":160,"width":160}]}],"albums":[{"id":"1ghzhhlGuTLCD790oXWJwX","name":"MTV Unplugged","images":[{"height":640,"url":"https:\/\/i.scdn.co\/image\/ab67616d0000b273add2474f5952482c05611f6c","width":640},{"height":300,"url":"https:\/\/i.scdn.co\/image\/ab67616d00001e02add2474f5952482c05611f6c","width":300},{"height":64,"url":"https:\/\/i.scdn.co\/image\/ab67616d00004851add2474f5952482c05611f6c","width":64}],"artists":[{"id":"1w5Kfo2jwwIPruYS2UWh56","name":"Pearl Jam"}]},{"id":"5B4PYA7wNN4WdEXdIJu58a","name":"Ten","images":[{"height":640,"url":"https:\/\/i.scdn.co\/image\/ab67616d0000b273d400d27cba05bb0545533864","width":640},{"height":300,"url":"https:\/\/i.scdn.co\/image\/ab67616d00001e02d400d27cba05bb0545533864","width":300},{"height":64,"url":"https:\/\/i.scdn.co\/image\/ab67616d00004851d400d27cba05bb0545533864","width":64}],"artists":[{"id":"1w5Kfo2jwwIPruYS2UWh56","name":"Pearl Jam"}]},{"id":"3BSOiAas8BpJOii3kCPyjV","name":"Vs.","images":[{"height":640,"url":"https:\/\/i.scdn.co\/image\/ab67616d0000b273777344aba9d5b5785b4593a5","width":640},{"height":300,"url":"https:\/\/i.scdn.co\/image\/ab67616d00001e02777344aba9d5b5785b4593a5","width":300},{"height":64,"url":"https:\/\/i.scdn.co\/image\/ab67616d00004851777344aba9d5b5785b4593a5","width":64}],"artists":[{"id":"1w5Kfo2jwwIPruYS2UWh56","name":"Pearl Jam"}]},{"id":"5zsDtoSrXK4usJ4MB1tCh2","name":"Yield","images":[{"height":640,"url":"https:\/\/i.scdn.co\/image\/ab67616d0000b273a53f06a45b489abe8f577134","width":640},{"height":300,"url":"https:\/\/i.scdn.co\/image\/ab67616d00001e02a53f06a45b489abe8f577134","width":300},{"height":64,"url":"https:\/\/i.scdn.co\/image\/ab67616d00004851a53f06a45b489abe8f577134","width":64}],"artists":[{"id":"1w5Kfo2jwwIPruYS2UWh56","name":"Pearl Jam"}]},{"id":"5pd9B3KQWKshHw4lnsSLNy","name":"Vitalogy","images":[{"height":640,"url":"https:\/\/i.scdn.co\/image\/ab67616d0000b273f0f6b8bc425633e6ed6369c4","width":640},{"height":300,"url":"https:\/\/i.scdn.co\/image\/ab67616d00001e02f0f6b8bc425633e6ed6369c4","width":300},{"height":64,"url":"https:\/\/i.scdn.co\/image\/ab67616d00004851f0f6b8bc425633e6ed6369c4","width":64}],"artists":[{"id":"1w5Kfo2jwwIPruYS2UWh56","name":"Pearl Jam"}]},{"id":"01WEcEzoa9mfh8fIDhvV1M","name":"Lightning Bolt","images":[{"height":640,"url":"https:\/\/i.scdn.co\/image\/ab67616d0000b273fa475954245b93ca3167469e","width":640},{"height":300,"url":"https:\/\/i.scdn.co\/image\/ab67616d00001e02fa475954245b93ca3167469e","width":300},{"height":64,"url":"https:\/\/i.scdn.co\/image\/ab67616d00004851fa475954245b93ca3167469e","width":64}],"artists":[{"id":"1w5Kfo2jwwIPruYS2UWh56","name":"Pearl Jam"}]},{"id":"5PY2mZGCOMezmWH7hiCwFH","name":"Pearl Jam","images":[{"height":640,"url":"https:\/\/i.scdn.co\/image\/ab67616d0000b273abd6980a0f2f2c9cc13581e0","width":640},{"height":300,"url":"https:\/\/i.scdn.co\/image\/ab67616d00001e02abd6980a0f2f2c9cc13581e0","width":300},{"height":64,"url":"https:\/\/i.scdn.co\/image\/ab67616d00004851abd6980a0f2f2c9cc13581e0","width":64}],"artists":[{"id":"1w5Kfo2jwwIPruYS2UWh56","name":"Pearl Jam"}]},{"id":"1z6iuIsvWR3AjWhMY2xFOk","name":"Pearl Jam Twenty Original Motion Picture Soundtrack","images":[{"height":640,"url":"https:\/\/i.scdn.co\/image\/ab67616d0000b2739ed6d44c0f918e686b691bce","width":640},{"height":300,"url":"https:\/\/i.scdn.co\/image\/ab67616d00001e029ed6d44c0f918e686b691bce","width":300},{"height":64,"url":"https:\/\/i.scdn.co\/image\/ab67616d000048519ed6d44c0f918e686b691bce","width":64}],"artists":[{"id":"1w5Kfo2jwwIPruYS2UWh56","name":"Pearl Jam"}]},{"id":"11BDZR6NRHwPiPy1WQr4Jf","name":"Last Kiss","images":[{"height":640,"url":"https:\/\/i.scdn.co\/image\/ab67616d0000b273d7db5abcbc899f3994c66fc6","width":640},{"height":300,"url":"https:\/\/i.scdn.co\/image\/ab67616d00001e02d7db5abcbc899f3994c66fc6","width":300},{"height":64,"url":"https:\/\/i.scdn.co\/image\/ab67616d00004851d7db5abcbc899f3994c66fc6","width":64}],"artists":[{"id":"1w5Kfo2jwwIPruYS2UWh56","name":"Pearl Jam"}]},{"id":"2lK5A62miDFduYER1l5j3P","name":"Saqi Saqi Jan Peala Pur Main","images":[{"height":640,"url":"https:\/\/i.scdn.co\/image\/ab67616d0000b273029f70042a13433e514357fe","width":640},{"height":300,"url":"https:\/\/i.scdn.co\/image\/ab67616d00001e02029f70042a13433e514357fe","width":300},{"height":64,"url":"https:\/\/i.scdn.co\/image\/ab67616d00004851029f70042a13433e514357fe","width":64}],"artists":[{"id":"6QDaDWrJLBZO3FDQpePfXU","name":"Jamshid Parwani"}]}],"playlists":[{"id":"5NY2aXBmyej83GL1tZezE9","name":"Pearl Jam - As Melhores","images":[{"height":null,"url":"https:\/\/image-cdn-ak.spotifycdn.com\/image\/ab67706c0000da8484ce59ddfd271b27bbd7e038","width":null}]},{"id":"2fjUyCkpHi0S3IUGaxqj4N","name":"Pearl Jam - S\u00f3 as melhores","images":[{"height":null,"url":"https:\/\/image-cdn-fa.spotifycdn.com\/image\/ab67706c0000d72c185b7ec7818956e104fb25ff","width":null}]},{"id":"1Edgb8018MlcfGnuB5xhX3","name":"Black \u2013 Pearl Jam","images":[{"height":null,"url":"https:\/\/image-cdn-ak.spotifycdn.com\/image\/ab67706c0000d72cea8d6138aa4baa069390114f","width":null}]},{"id":"1eKgV50PpOx6nZqZA5pugS","name":"Pearl Jam, Creed, Nirvana, Audioslave","images":[{"height":640,"url":"https:\/\/mosaic.scdn.co\/640\/ab67616d00001e028df1fdc14be33eb2c991d60fab67616d00001e02a32f2ae4dade83e0d7a294f4ab67616d00001e02d400d27cba05bb0545533864ab67616d00001e02d7db5abcbc899f3994c66fc6","width":640},{"height":300,"url":"https:\/\/mosaic.scdn.co\/300\/ab67616d00001e028df1fdc14be33eb2c991d60fab67616d00001e02a32f2ae4dade83e0d7a294f4ab67616d00001e02d400d27cba05bb0545533864ab67616d00001e02d7db5abcbc899f3994c66fc6","width":300},{"height":60,"url":"https:\/\/mosaic.scdn.co\/60\/ab67616d00001e028df1fdc14be33eb2c991d60fab67616d00001e02a32f2ae4dade83e0d7a294f4ab67616d00001e02d400d27cba05bb0545533864ab67616d00001e02d7db5abcbc899f3994c66fc6","width":60}]},{"id":"4BWdcaxeNL1kmVjGEj3vxh","name":"Rock Anos 90 e 2000 Internacional. As melhores!","images":[{"height":null,"url":"https:\/\/image-cdn-ak.spotifycdn.com\/image\/ab67706c0000d72c5b9d00469d5206b19f346676","width":null}]},{"id":"1lNvZ9qRbgfL9lqCsFld95","name":"peal jam ","images":[{"height":640,"url":"https:\/\/mosaic.scdn.co\/640\/ab67616d00001e02777344aba9d5b5785b4593a5ab67616d00001e028df1fdc14be33eb2c991d60fab67616d00001e02d400d27cba05bb0545533864ab67616d00001e02d7db5abcbc899f3994c66fc6","width":640},{"height":300,"url":"https:\/\/mosaic.scdn.co\/300\/ab67616d00001e02777344aba9d5b5785b4593a5ab67616d00001e028df1fdc14be33eb2c991d60fab67616d00001e02d400d27cba05bb0545533864ab67616d00001e02d7db5abcbc899f3994c66fc6","width":300},{"height":60,"url":"https:\/\/mosaic.scdn.co\/60\/ab67616d00001e02777344aba9d5b5785b4593a5ab67616d00001e028df1fdc14be33eb2c991d60fab67616d00001e02d400d27cba05bb0545533864ab67616d00001e02d7db5abcbc899f3994c66fc6","width":60}]},{"id":"2GQ3rqFPpXgYgIChRXXki4","name":"pealr jam","images":[{"height":640,"url":"https:\/\/mosaic.scdn.co\/640\/ab67616d00001e02777344aba9d5b5785b4593a5ab67616d00001e02a20dd7a979699da6dce878aeab67616d00001e02a53f06a45b489abe8f577134ab67616d00001e02f0f6b8bc425633e6ed6369c4","width":640},{"height":300,"url":"https:\/\/mosaic.scdn.co\/300\/ab67616d00001e02777344aba9d5b5785b4593a5ab67616d00001e02a20dd7a979699da6dce878aeab67616d00001e02a53f06a45b489abe8f577134ab67616d00001e02f0f6b8bc425633e6ed6369c4","width":300},{"height":60,"url":"https:\/\/mosaic.scdn.co\/60\/ab67616d00001e02777344aba9d5b5785b4593a5ab67616d00001e02a20dd7a979699da6dce878aeab67616d00001e02a53f06a45b489abe8f577134ab67616d00001e02f0f6b8bc425633e6ed6369c4","width":60}]},{"id":"6RaRhyi84y6zhv3gswNq2T","name":"O melhor do Rock","images":[{"height":640,"url":"https:\/\/mosaic.scdn.co\/640\/ab67616d00001e0252cbfb62c42adc19d5637843ab67616d00001e02866c0774471b4d4a5129bb83ab67616d00001e02cc2478157cda3f07b9b908e7ab67616d00001e02e71708b667804f6241dd1a59","width":640},{"height":300,"url":"https:\/\/mosaic.scdn.co\/300\/ab67616d00001e0252cbfb62c42adc19d5637843ab67616d00001e02866c0774471b4d4a5129bb83ab67616d00001e02cc2478157cda3f07b9b908e7ab67616d00001e02e71708b667804f6241dd1a59","width":300},{"height":60,"url":"https:\/\/mosaic.scdn.co\/60\/ab67616d00001e0252cbfb62c42adc19d5637843ab67616d00001e02866c0774471b4d4a5129bb83ab67616d00001e02cc2478157cda3f07b9b908e7ab67616d00001e02e71708b667804f6241dd1a59","width":60}]}],"podcasts":[{"id":"14jalMOh1Jr77eTRUdN6X9","name":"Intelig\u00eancia Ltda.","publisher":"Rog\u00e9rio Vilela","images":[{"height":640,"url":"https:\/\/i.scdn.co\/image\/ab6765630000ba8a7fbf5d3b676ba83b4a1867b3","width":640},{"height":300,"url":"https:\/\/i.scdn.co\/image\/ab67656300005f1f7fbf5d3b676ba83b4a1867b3","width":300},{"height":64,"url":"https:\/\/i.scdn.co\/image\/ab6765630000f68d7fbf5d3b676ba83b4a1867b3","width":64}]},{"id":"3V5LBozjo4vNg2oJoA4Wb2","name":"Flow Podcast","publisher":"Grupo Flow","images":[{"height":640,"url":"https:\/\/i.scdn.co\/image\/ab6765630000ba8a28c5bbf0560908592d537e3b","width":640},{"height":300,"url":"https:\/\/i.scdn.co\/image\/ab67656300005f1f28c5bbf0560908592d537e3b","width":300},{"height":64,"url":"https:\/\/i.scdn.co\/image\/ab6765630000f68d28c5bbf0560908592d537e3b","width":64}]},{"id":"7eJGd9HVEPmrg7RqSpEhuZ","name":"PeeWeeCast","publisher":"Canal PeeWee","images":[{"height":640,"url":"https:\/\/i.scdn.co\/image\/ab6765630000ba8a8b921903f77acc57b1183225","width":640},{"height":300,"url":"https:\/\/i.scdn.co\/image\/ab67656300005f1f8b921903f77acc57b1183225","width":300},{"height":64,"url":"https:\/\/i.scdn.co\/image\/ab6765630000f68d8b921903f77acc57b1183225","width":64}]},{"id":"58dDhw54MbfbfeePyHO9j8","name":"State of Love & Trust: A Pearl Jam Podcast","publisher":"Jason Kerepesi & Paul Ghiglieri","images":[{"height":640,"url":"https:\/\/i.scdn.co\/image\/ab6765630000ba8a466f62781fefe76bc92f5ce6","width":640},{"height":300,"url":"https:\/\/i.scdn.co\/image\/ab67656300005f1f466f62781fefe76bc92f5ce6","width":300},{"height":64,"url":"https:\/\/i.scdn.co\/image\/ab6765630000f68d466f62781fefe76bc92f5ce6","width":64}]},{"id":"4qVTyDKR4jd0mGL3oSjLo5","name":"Single Podcast Theory - A Pearl Jam Podcast","publisher":"Brad Lyons and Brad Blazek","images":[{"height":640,"url":"https:\/\/i.scdn.co\/image\/ab6765630000ba8ab0a9a876f2af9b8c46a68093","width":640},{"height":300,"url":"https:\/\/i.scdn.co\/image\/ab67656300005f1fb0a9a876f2af9b8c46a68093","width":300},{"height":64,"url":"https:\/\/i.scdn.co\/image\/ab6765630000f68db0a9a876f2af9b8c46a68093","width":64}]},{"id":"6AIQNh5MkV7Ms2iWZQ3cU8","name":"Pearl Jam ","publisher":"nina schmidt","images":[{"height":640,"url":"https:\/\/i.scdn.co\/image\/ab6765630000ba8a593f1f01cbfc91c2aeaf849b","width":640},{"height":300,"url":"https:\/\/i.scdn.co\/image\/ab67656300005f1f593f1f01cbfc91c2aeaf849b","width":300},{"height":64,"url":"https:\/\/i.scdn.co\/image\/ab6765630000f68d593f1f01cbfc91c2aeaf849b","width":64}]},{"id":"02IVgYlYfqkYo91oNvglI5","name":"Pearl Jam dalla A alla Z","publisher":"pearljamonline.it","images":[{"height":640,"url":"https:\/\/i.scdn.co\/image\/ab6765630000ba8a54b00523cfa86bc278d7529f","width":640},{"height":300,"url":"https:\/\/i.scdn.co\/image\/ab67656300005f1f54b00523cfa86bc278d7529f","width":300},{"height":64,"url":"https:\/\/i.scdn.co\/image\/ab6765630000f68d54b00523cfa86bc278d7529f","width":64}]},{"id":"1A14VN23wNz4AXU7UTUEzg","name":"The Rawle & Gene Show: The Power of Coaching","publisher":"Pealed Back","images":[{"height":640,"url":"https:\/\/i.scdn.co\/image\/ab6765630000ba8a4b4a525061f78d91fddfa446","width":640},{"height":300,"url":"https:\/\/i.scdn.co\/image\/ab67656300005f1f4b4a525061f78d91fddfa446","width":300},{"height":64,"url":"https:\/\/i.scdn.co\/image\/ab6765630000f68d4b4a525061f78d91fddfa446","width":64}]},{"id":"2NNblMHxoxCLs9TtRtr12T","name":"SECRETS OF SUCCESS: Masters' Greatest Wisdom","publisher":"The Secrets of Success","images":[{"height":640,"url":"https:\/\/i.scdn.co\/image\/ab6765630000ba8a3c1c7489accc5952ac0258b1","width":640},{"height":300,"url":"https:\/\/i.scdn.co\/image\/ab67656300005f1f3c1c7489accc5952ac0258b1","width":300},{"height":64,"url":"https:\/\/i.scdn.co\/image\/ab6765630000f68d3c1c7489accc5952ac0258b1","width":64}]},{"id":"7M5Kborn4yozY8OqAaMmbX","name":"The Mayo Jam","publisher":"MCGS Alumni","images":[{"height":640,"url":"https:\/\/i.scdn.co\/image\/ab6765630000ba8adedd36c15499cd5fd8087fb0","width":640},{"height":300,"url":"https:\/\/i.scdn.co\/image\/ab67656300005f1fdedd36c15499cd5fd8087fb0","width":300},{"height":64,"url":"https:\/\/i.scdn.co\/image\/ab6765630000f68ddedd36c15499cd5fd8087fb0","width":64}]}],"tracks":[{"id":"5Xak5fmy089t0FYmh3VJiY","name":"Black","popularity":79,"images":[{"height":640,"width":640,"url":"https:\/\/i.scdn.co\/image\/ab67616d0000b273d400d27cba05bb0545533864"},{"height":300,"width":300,"url":"https:\/\/i.scdn.co\/image\/ab67616d00001e02d400d27cba05bb0545533864"},{"height":64,"width":64,"url":"https:\/\/i.scdn.co\/image\/ab67616d00004851d400d27cba05bb0545533864"}],"artists":[{"id":"1w5Kfo2jwwIPruYS2UWh56","name":"Pearl Jam"}],"duration_ms":342653},{"id":"6QewNVIDKdSl8Y3ycuHIei","name":"Even Flow","popularity":82,"images":[{"height":640,"width":640,"url":"https:\/\/i.scdn.co\/image\/ab67616d0000b273d400d27cba05bb0545533864"},{"height":300,"width":300,"url":"https:\/\/i.scdn.co\/image\/ab67616d00001e02d400d27cba05bb0545533864"},{"height":64,"width":64,"url":"https:\/\/i.scdn.co\/image\/ab67616d00004851d400d27cba05bb0545533864"}],"artists":[{"id":"1w5Kfo2jwwIPruYS2UWh56","name":"Pearl Jam"}],"duration_ms":292580},{"id":"62nQ8UZVqR2RMvkJHkcO2o","name":"Jeremy","popularity":74,"images":[{"height":640,"width":640,"url":"https:\/\/i.scdn.co\/image\/ab67616d0000b273d400d27cba05bb0545533864"},{"height":300,"width":300,"url":"https:\/\/i.scdn.co\/image\/ab67616d00001e02d400d27cba05bb0545533864"},{"height":64,"width":64,"url":"https:\/\/i.scdn.co\/image\/ab67616d00004851d400d27cba05bb0545533864"}],"artists":[{"id":"1w5Kfo2jwwIPruYS2UWh56","name":"Pearl Jam"}],"duration_ms":318226},{"id":"1L94M3KIu7QluZe63g64rv","name":"Alive","popularity":78,"images":[{"height":640,"width":640,"url":"https:\/\/i.scdn.co\/image\/ab67616d0000b273d400d27cba05bb0545533864"},{"height":300,"width":300,"url":"https:\/\/i.scdn.co\/image\/ab67616d00001e02d400d27cba05bb0545533864"},{"height":64,"width":64,"url":"https:\/\/i.scdn.co\/image\/ab67616d00004851d400d27cba05bb0545533864"}],"artists":[{"id":"1w5Kfo2jwwIPruYS2UWh56","name":"Pearl Jam"}],"duration_ms":340907},{"id":"06vyBAqzokvXjw3b7FPcZi","name":"Something Special","popularity":49,"images":[{"height":640,"width":640,"url":"https:\/\/i.scdn.co\/image\/ab67616d0000b2736fcdcbbd9cae9001ca5b20d5"},{"height":300,"width":300,"url":"https:\/\/i.scdn.co\/image\/ab67616d00001e026fcdcbbd9cae9001ca5b20d5"},{"height":64,"width":64,"url":"https:\/\/i.scdn.co\/image\/ab67616d000048516fcdcbbd9cae9001ca5b20d5"}],"artists":[{"id":"1w5Kfo2jwwIPruYS2UWh56","name":"Pearl Jam"}],"duration_ms":246877},{"id":"083LM23MmqS8HTTYZQrYxG","name":"Wreckage","popularity":59,"images":[{"height":640,"width":640,"url":"https:\/\/i.scdn.co\/image\/ab67616d0000b2736fcdcbbd9cae9001ca5b20d5"},{"height":300,"width":300,"url":"https:\/\/i.scdn.co\/image\/ab67616d00001e026fcdcbbd9cae9001ca5b20d5"},{"height":64,"width":64,"url":"https:\/\/i.scdn.co\/image\/ab67616d000048516fcdcbbd9cae9001ca5b20d5"}],"artists":[{"id":"1w5Kfo2jwwIPruYS2UWh56","name":"Pearl Jam"}],"duration_ms":300487},{"id":"0S4VR8n0KBkE6DxrjArswJ","name":"Dark Matter","popularity":55,"images":[{"height":640,"width":640,"url":"https:\/\/i.scdn.co\/image\/ab67616d0000b2736fcdcbbd9cae9001ca5b20d5"},{"height":300,"width":300,"url":"https:\/\/i.scdn.co\/image\/ab67616d00001e026fcdcbbd9cae9001ca5b20d5"},{"height":64,"width":64,"url":"https:\/\/i.scdn.co\/image\/ab67616d000048516fcdcbbd9cae9001ca5b20d5"}],"artists":[{"id":"1w5Kfo2jwwIPruYS2UWh56","name":"Pearl Jam"}],"duration_ms":211720},{"id":"6J8WWhBp4S7MA9yCT64wvB","name":"Peal for John Cook","popularity":0,"images":[{"height":640,"width":640,"url":"https:\/\/i.scdn.co\/image\/ab67616d0000b273f2dc7d23076e140e779e4026"},{"height":300,"width":300,"url":"https:\/\/i.scdn.co\/image\/ab67616d00001e02f2dc7d23076e140e779e4026"},{"height":64,"width":64,"url":"https:\/\/i.scdn.co\/image\/ab67616d00004851f2dc7d23076e140e779e4026"}],"artists":[{"id":"1vN7ZlRrysSyvzfFTfR5vS","name":"Peter James"}],"duration_ms":138634},{"id":"2nIRn017AveW1A76f174cr","name":"PEAL OF HOPE","popularity":0,"images":[{"height":640,"width":640,"url":"https:\/\/i.scdn.co\/image\/ab67616d0000b273e4c30e4863490da0cb17a029"},{"height":300,"width":300,"url":"https:\/\/i.scdn.co\/image\/ab67616d00001e02e4c30e4863490da0cb17a029"},{"height":64,"width":64,"url":"https:\/\/i.scdn.co\/image\/ab67616d00004851e4c30e4863490da0cb17a029"}],"artists":[{"id":"7CQCH9gbsm8L7T4NmqgxfZ","name":"James Edward Collins"}],"duration_ms":185618},{"id":"3ihUBhBlj4Q0Vg7CKDdfbC","name":"Saqi Saqi Jan Peala Pur Main","popularity":0,"images":[{"height":640,"width":640,"url":"https:\/\/i.scdn.co\/image\/ab67616d0000b273029f70042a13433e514357fe"},{"height":300,"width":300,"url":"https:\/\/i.scdn.co\/image\/ab67616d00001e02029f70042a13433e514357fe"},{"height":64,"width":64,"url":"https:\/\/i.scdn.co\/image\/ab67616d00004851029f70042a13433e514357fe"}],"artists":[{"id":"6QDaDWrJLBZO3FDQpePfXU","name":"Jamshid Parwani"}],"duration_ms":303856}],"best_result":{"type":"artist","id":"1w5Kfo2jwwIPruYS2UWh56","name":"Pearl Jam","popularity":77,"images":[{"url":"https:\/\/i.scdn.co\/image\/ab6761610000e5ebe431fb8ba17cdee73e4ce08a","height":640,"width":640},{"url":"https:\/\/i.scdn.co\/image\/ab67616100005174e431fb8ba17cdee73e4ce08a","height":320,"width":320},{"url":"https:\/\/i.scdn.co\/image\/ab6761610000f178e431fb8ba17cdee73e4ce08a","height":160,"width":160}],"artists":[{"id":"1w5Kfo2jwwIPruYS2UWh56","name":"Pearl Jam"}]}}