{"artists":[{"id":"1Yox196W7bzVNZI7RBaPnf","name":"Megadeth","popularity":71,"images":[{"url":"https:\/\/i.scdn.co\/image\/ab6761610000e5eb3f19bad1d41dceb90d8b4cf5","height":640,"width":640},{"url":"https:\/\/i.scdn.co\/image\/ab676161000051743f19bad1d41dceb90d8b4cf5","height":320,"width":320},{"url":"https:\/\/i.scdn.co\/image\/ab6761610000f1783f19bad1d41dceb90d8b4cf5","height":160,"width":160}]},{"id":"181bsRPaVXVlUKXrxwZfHK","name":"Megan Thee Stallion","popularity":80,"images":[{"url":"https:\/\/i.scdn.co\/image\/ab6761610000e5eba300c2e412844ab60e397b1b","height":640,"width":640},{"url":"https:\/\/i.scdn.co\/image\/ab67616100005174a300c2e412844ab60e397b1b","height":320,"width":320},{"url":"https:\/\/i.scdn.co\/image\/ab6761610000f178a300c2e412844ab60e397b1b","height":160,"width":160}]},{"id":"6JL8zeS1NmiOftqZTRgdTz","name":"Meghan Trainor","popularity":78,"images":[{"url":"https:\/\/i.scdn.co\/image\/ab6761610000e5eb365984489dac7a79eac204e3","height":640,"width":640},{"url":"https:\/\/i.scdn.co\/image\/ab67616100005174365984489dac7a79eac204e3","height":320,"width":320},{"url":"https:\/\/i.scdn.co\/image\/ab6761610000f178365984489dac7a79eac204e3","height":160,"width":160}]},{"id":"6EHs7rGH4jgLSNezIy9i3F","name":"Megabaile Do Areias","popularity":42,"images":[{"url":"https:\/\/i.scdn.co\/image\/ab6761610000e5eb9a9e296d9d0ca84585271a73","height":640,"width":640},{"url":"https:\/\/i.scdn.co\/image\/ab676161000051749a9e296d9d0ca84585271a73","height":320,"width":320},{"url":"https:\/\/i.scdn.co\/image\/ab6761610000f1789a9e296d9d0ca84585271a73","height":160,"width":160}]},{"id":"5Ppie0uPnbnvGBYRwYmlt0","name":"Megan Moroney","popularity":76,"images":[{"url":"https:\/\/i.scdn.co\/image\/ab6761610000e5ebd0eb86d3ac3beaad7efb77d8","height":640,"width":640},{"url":"https:\/\/i.scdn.co\/image\/ab67616100005174d0eb86d3ac3beaad7efb77d8","height":320,"width":320},{"url":"https:\/\/i.scdn.co\/image\/ab6761610000f178d0eb86d3ac3beaad7efb77d8","height":160,"width":160}]},{"id":"7rQcqKz9Ige4STuodC9nzt","name":"Mega","popularity":5,"images":[{"url":"https:\/\/i.scdn.co\/image\/ab6761610000e5eb990f26eaaa80514f7605240e","height":640,"width":640},{"url":"https:\/\/i.scdn.co\/image\/ab67616100005174990f26eaaa80514f7605240e","height":320,"width":320},{"url":"https:\/\/i.scdn.co\/image\/ab6761610000f178990f26eaaa80514f7605240e","height":160,"width":160}]},{"id":"45xGatk4AWq9yzqOfolEWg","name":"Mega","popularity":49,"images":[{"url":"https:\/\/i.scdn.co\/image\/ab6761610000e5eb9fd53dd036527c159de61731","height":640,"width":640},{"url":"https:\/\/i.scdn.co\/image\/ab676161000051749fd53dd036527c159de61731","height":320,"width":320},{"url":"https:\/\/i.scdn.co\/image\/ab6761610000f1789fd53dd036527c159de61731","height":160,"width":160}]},{"id":"1HY2Jd0NmPuamShAr6KMms","name":"Lady Gaga","popularity":94,"images":[{"url":"https:\/\/i.scdn.co\/image\/ab6761610000e5ebaadc18cac8d48124357c38e6","height":640,"width":640},{"url":"https:\/\/i.scdn.co\/image\/ab67616100005174aadc18cac8d48124357c38e6","height":320,"width":320},{"url":"https:\/\/i.scdn.co\/image\/ab6761610000f178aadc18cac8d48124357c38e6","height":160,"width":160}]},{"id":"5KJO8SHDZrO7mvLq0FKu7b","name":"Mega","popularity":45,"images":[{"url":"https:\/\/i.scdn.co\/image\/ab6761610000e5eb06b8b08da91e6317ae23df6d","height":640,"width":640},{"url":"https:\/\/i.scdn.co\/image\/ab6761610000517406b8b08da91e6317ae23df6d","height":320,"width":320},{"url":"https:\/\/i.scdn.co\/image\/ab6761610000f17806b8b08da91e6317ae23df6d","height":160,"width":160}]},{"id":"51KISDfsefyPBbbqecMFRP","name":"Mega","popularity":50,"images":[]}],"albums":[{"id":"66XmdaeHLxkgUZSzxa9tNM","name":"Mega","images":[{"height":640,"url":"https:\/\/i.scdn.co\/image\/ab67616d0000b2734e686f2657a4b64611a8b7cb","width":640},{"height":300,"url":"https:\/\/i.scdn.co\/image\/ab67616d00001e024e686f2657a4b64611a8b7cb","width":300},{"height":64,"url":"https:\/\/i.scdn.co\/image\/ab67616d000048514e686f2657a4b64611a8b7cb","width":64}],"artists":[{"id":"38Tgg9D2XnpKvUC5tjydon","name":"Battlemode"}]},{"id":"3gd8bZ8YFQ5YNF1B5ChTLj","name":"MEGA THE RIDDLE","images":[{"height":640,"url":"https:\/\/i.scdn.co\/image\/ab67616d0000b27350785d5bafb84b090cc32175","width":640},{"height":300,"url":"https:\/\/i.scdn.co\/image\/ab67616d00001e0250785d5bafb84b090cc32175","width":300},{"height":64,"url":"https:\/\/i.scdn.co\/image\/ab67616d0000485150785d5bafb84b090cc32175","width":64}],"artists":[{"id":"4a9zpH5ecVcDucEpygddWO","name":"Go!Beatz"},{"id":"61p9Lxms7fy21FDl7Ur9DF","name":"DJ PEDRO MARTINS"},{"id":"1C7swBbZLPAFNdk5nFGwgC","name":"FARIAS"}]},{"id":"39DHfPnyAgpDM4OrkFOjHh","name":"MEGA HOUSE 1.0","images":[{"height":640,"url":"https:\/\/i.scdn.co\/image\/ab67616d0000b27331297c0b7c6ec72f6a3044ed","width":640},{"height":300,"url":"https:\/\/i.scdn.co\/image\/ab67616d00001e0231297c0b7c6ec72f6a3044ed","width":300},{"height":64,"url":"https:\/\/i.scdn.co\/image\/ab67616d0000485131297c0b7c6ec72f6a3044ed","width":64}],"artists":[{"id":"4s5nNjzkiR86KcvG5Xnuuk","name":"GUSTA SC"}]},{"id":"7vUwWLTxwHH6a7shjaSHCC","name":"Mega do Pampeiro","images":[{"height":640,"url":"https:\/\/i.scdn.co\/image\/ab67616d0000b27356cf7883fb26b3efd6fdb6b9","width":640},{"height":300,"url":"https:\/\/i.scdn.co\/image\/ab67616d00001e0256cf7883fb26b3efd6fdb6b9","width":300},{"height":64,"url":"https:\/\/i.scdn.co\/image\/ab67616d0000485156cf7883fb26b3efd6fdb6b9","width":64}],"artists":[{"id":"4Vy4r3LI5EujHDewjGuIp8","name":"DJ LMB"},{"id":"4jEl4IQK6F0OECbeeatBBM","name":"Mc Sapinha"},{"id":"3l4fsEzoeabsET7ddv0lZW","name":"Mc Delux"}]},{"id":"6AemlydyzBrwH6kWa3OmZN","name":"Mega Ritmista Glaison Willians","images":[{"height":640,"url":"https:\/\/i.scdn.co\/image\/ab67616d0000b27347b44b006e76678aef549e3f","width":640},{"height":300,"url":"https:\/\/i.scdn.co\/image\/ab67616d00001e0247b44b006e76678aef549e3f","width":300},{"height":64,"url":"https:\/\/i.scdn.co\/image\/ab67616d0000485147b44b006e76678aef549e3f","width":64}],"artists":[{"id":"0f1IECbrVV952unZkzrsg2","name":"Mc Gw"},{"id":"651jNHJzsX4ckQvURNNAIS","name":"DJ YUZAK"}]},{"id":"48oNqLhPuckGCSUZ7HXra7","name":"Mega Perreo Motoka","images":[{"height":640,"url":"https:\/\/i.scdn.co\/image\/ab67616d0000b2735e453dfc5d7ccafff47aa3ee","width":640},{"height":300,"url":"https:\/\/i.scdn.co\/image\/ab67616d00001e025e453dfc5d7ccafff47aa3ee","width":300},{"height":64,"url":"https:\/\/i.scdn.co\/image\/ab67616d000048515e453dfc5d7ccafff47aa3ee","width":64}],"artists":[{"id":"22L9gxTv3H8kh9o4W84m3O","name":"DJ Carlos Martinez"},{"id":"097U2TxCM50LKrVNHg7ulB","name":"ELG0RD0LIND0MDF"},{"id":"1fJmhlwwsRZfAgkahD5I73","name":"TRATTO DE LA CALLE"}]},{"id":"6bfDdDxNcI19EdjfVpkqkU","name":"Mega","images":[{"height":640,"url":"https:\/\/i.scdn.co\/image\/ab67616d0000b2735b0400b555f53c5b8d59dc0d","width":640},{"height":300,"url":"https:\/\/i.scdn.co\/image\/ab67616d00001e025b0400b555f53c5b8d59dc0d","width":300},{"height":64,"url":"https:\/\/i.scdn.co\/image\/ab67616d000048515b0400b555f53c5b8d59dc0d","width":64}],"artists":[{"id":"1oR9pQhucVTJyi5lH2Y2iT","name":"Blank Banshee"}]},{"id":"2TMyhElmeH3LShkpsI2qCK","name":"Mega","images":[{"height":640,"url":"https:\/\/i.scdn.co\/image\/ab67616d0000b2730519bd526204b6f94c38f81b","width":640},{"height":300,"url":"https:\/\/i.scdn.co\/image\/ab67616d00001e020519bd526204b6f94c38f81b","width":300},{"height":64,"url":"https:\/\/i.scdn.co\/image\/ab67616d000048510519bd526204b6f94c38f81b","width":64}],"artists":[{"id":"5noxI0pLmlTP3REOFdD2PB","name":"Megalodom"}]},{"id":"2chEldiRKaCzLqk4rpUj6V","name":"Mega","images":[{"height":640,"url":"https:\/\/i.scdn.co\/image\/ab67616d0000b273e186e06f0ce7c35430749896","width":640},{"height":300,"url":"https:\/\/i.scdn.co\/image\/ab67616d00001e02e186e06f0ce7c35430749896","width":300},{"height":64,"url":"https:\/\/i.scdn.co\/image\/ab67616d00004851e186e06f0ce7c35430749896","width":64}],"artists":[{"id":"3JfIPcjATed1eJMF4kHkCs","name":"Built By Snow"}]},{"id":"4V14ntAavm3i5BIB5CNNTu","name":"Mega (10th Anniversary Edition)","images":[{"height":640,"url":"https:\/\/i.scdn.co\/image\/ab67616d0000b273b538cfc0cad4b48d811a5abc","width":640},{"height":300,"url":"https:\/\/i.scdn.co\/image\/ab67616d00001e02b538cfc0cad4b48d811a5abc","width":300},{"height":64,"url":"https:\/\/i.scdn.co\/image\/ab67616d00004851b538cfc0cad4b48d811a5abc","width":64}],"artists":[{"id":"4WmEJkzJ7Z3yeIa98QS93Y","name":"Alexander Marcus"}]}],"playlists":[{"id":"4PsJPMQlMphZ71MZfmrOZd","name":"Megadeth","images":[{"height":640,"url":"https:\/\/mosaic.scdn.co\/640\/ab67616d00001e020f783e735d0f43f071109a90ab67616d00001e027b178f928742be1492c6fba2ab67616d00001e02be9fa5a89479b6af481938a0ab67616d00001e02d408b2375e0ca6362c968d0f","width":640},{"height":300,"url":"https:\/\/mosaic.scdn.co\/300\/ab67616d00001e020f783e735d0f43f071109a90ab67616d00001e027b178f928742be1492c6fba2ab67616d00001e02be9fa5a89479b6af481938a0ab67616d00001e02d408b2375e0ca6362c968d0f","width":300},{"height":60,"url":"https:\/\/mosaic.scdn.co\/60\/ab67616d00001e020f783e735d0f43f071109a90ab67616d00001e027b178f928742be1492c6fba2ab67616d00001e02be9fa5a89479b6af481938a0ab67616d00001e02d408b2375e0ca6362c968d0f","width":60}]},{"id":"2doPIBr4tUbMkvG5nVyp4s","name":"AS Melhores do Megadeth","images":[{"height":640,"url":"https:\/\/mosaic.scdn.co\/640\/ab67616d00001e020f783e735d0f43f071109a90ab67616d00001e027b178f928742be1492c6fba2ab67616d00001e02be9fa5a89479b6af481938a0ab67616d00001e02e949e0e6c9eac438a68f5b37","width":640},{"height":300,"url":"https:\/\/mosaic.scdn.co\/300\/ab67616d00001e020f783e735d0f43f071109a90ab67616d00001e027b178f928742be1492c6fba2ab67616d00001e02be9fa5a89479b6af481938a0ab67616d00001e02e949e0e6c9eac438a68f5b37","width":300},{"height":60,"url":"https:\/\/mosaic.scdn.co\/60\/ab67616d00001e020f783e735d0f43f071109a90ab67616d00001e027b178f928742be1492c6fba2ab67616d00001e02be9fa5a89479b6af481938a0ab67616d00001e02e949e0e6c9eac438a68f5b37","width":60}]},{"id":"2GT4B7GnaOMV1xEEPswPAQ","name":"MEGA FUNK 2025 \ud83d\udd25\ud83d\udd09 S\u00d3 OS MELHORES MEGAS","images":[{"height":null,"url":"https:\/\/image-cdn-ak.spotifycdn.com\/image\/ab67706c0000d72c670bb018b4e50f5f90d00e49","width":null}]},{"id":"4bjvaD0NTZCn6I6hlgeq7B","name":"Mega Gurizada do P\u00f3 \ud83d\udd09","images":[{"height":null,"url":"https:\/\/image-cdn-ak.spotifycdn.com\/image\/ab67706c0000da844be186b5efaf7e38fa46a8e8","width":null}]},{"id":"5Ww3D52QT7l3ZEFHllOH2E","name":"MEGA FUNK 2025 \ud83d\ude08 OS MELHORES E ATUALIZADOS","images":[{"height":null,"url":"https:\/\/image-cdn-ak.spotifycdn.com\/image\/ab67706c0000da84e32deaf8185d6895b6fb9879","width":null}]},{"id":"7hGdprAhOTXbNcKWygVvTW","name":"MEGA FUNK ATUALIZADO 2025 \ud83d\udca5\ud83d\udd1e","images":[{"height":null,"url":"https:\/\/image-cdn-ak.spotifycdn.com\/image\/ab67706c0000da84945ec62310b04ab233b22639","width":null}]},{"id":"0YQRuSbKkVDeBlTri2qFJG","name":"MEGA FUNK - DAS ANTIGAS","images":[{"height":640,"url":"https:\/\/mosaic.scdn.co\/640\/ab67616d00001e021e9df68a3f2b14cec0188c1cab67616d00001e024662cb014790b9474cb0648dab67616d00001e029232d00ef096dbbc570293e3ab67616d00001e02c719cd2f243cf769c6a28520","width":640},{"height":300,"url":"https:\/\/mosaic.scdn.co\/300\/ab67616d00001e021e9df68a3f2b14cec0188c1cab67616d00001e024662cb014790b9474cb0648dab67616d00001e029232d00ef096dbbc570293e3ab67616d00001e02c719cd2f243cf769c6a28520","width":300},{"height":60,"url":"https:\/\/mosaic.scdn.co\/60\/ab67616d00001e021e9df68a3f2b14cec0188c1cab67616d00001e024662cb014790b9474cb0648dab67616d00001e029232d00ef096dbbc570293e3ab67616d00001e02c719cd2f243cf769c6a28520","width":60}]},{"id":"7sMZTyxZGozbs9yyDhQMm5","name":"MTG 2025 ATUALIZADO \u2b50\ufe0f MAIS TOCADAS | MONTAGEM | QUEM NAO QUER SOU EU | QUERO TE ENCONTRAR | MEGA","images":[{"height":null,"url":"https:\/\/image-cdn-ak.spotifycdn.com\/image\/ab67706c0000da8437ae5e10a41ccb955ef92b2c","width":null}]}],"podcasts":[{"id":"2d82glPE2lfhOhnuz9C8CS","name":"\u00c1REA 54 ESPECIAL FORMULA TRUCK","publisher":"felipe_schmitz","images":[{"height":640,"url":"https:\/\/i.scdn.co\/image\/ab6765630000ba8a78b2e8ce4a87d36013e107a8","width":640},{"height":300,"url":"https:\/\/i.scdn.co\/image\/ab67656300005f1f78b2e8ce4a87d36013e107a8","width":300},{"height":64,"url":"https:\/\/i.scdn.co\/image\/ab6765630000f68d78b2e8ce4a87d36013e107a8","width":64}]},{"id":"2yBy3NYZluf7Yodsri42qp","name":"MEGA FUNK - COP\u00c3O NA M\u00c3O - 2018 (DJ David Rodrigues)","publisher":"Savenhago","images":[{"height":640,"url":"https:\/\/i.scdn.co\/image\/ab6765630000ba8ae67bde6962bb0dab6873d80c","width":640},{"height":300,"url":"https:\/\/i.scdn.co\/image\/ab67656300005f1fe67bde6962bb0dab6873d80c","width":300},{"height":64,"url":"https:\/\/i.scdn.co\/image\/ab6765630000f68de67bde6962bb0dab6873d80c","width":64}]},{"id":"1cXlpdOAa6nAYLxczekW3y","name":"Like a G6- Megan Freestyle","publisher":"Megan Thee Stallion ","images":[{"height":640,"url":"https:\/\/i.scdn.co\/image\/ab6765630000ba8a799094532e37ae9ef31c0bea","width":640},{"height":300,"url":"https:\/\/i.scdn.co\/image\/ab67656300005f1f799094532e37ae9ef31c0bea","width":300},{"height":64,"url":"https:\/\/i.scdn.co\/image\/ab6765630000f68d799094532e37ae9ef31c0bea","width":64}]},{"id":"116kLQ7H9hzpX6ARaAMlDv","name":"Dark Asia with Megan","publisher":"Megan Lee, Bleav","images":[{"height":640,"url":"https:\/\/i.scdn.co\/image\/ab6765630000ba8ae35114707c1c39ccac2f3c03","width":640},{"height":300,"url":"https:\/\/i.scdn.co\/image\/ab67656300005f1fe35114707c1c39ccac2f3c03","width":300},{"height":64,"url":"https:\/\/i.scdn.co\/image\/ab6765630000f68de35114707c1c39ccac2f3c03","width":64}]},{"id":"4jKvmWPjSwCSLHyQDZEjAt","name":"MegaCast","publisher":"MegaWhat","images":[{"height":640,"url":"https:\/\/i.scdn.co\/image\/ab6765630000ba8ab45832f3e703c0baa2bffd0b","width":640},{"height":300,"url":"https:\/\/i.scdn.co\/image\/ab67656300005f1fb45832f3e703c0baa2bffd0b","width":300},{"height":64,"url":"https:\/\/i.scdn.co\/image\/ab6765630000f68db45832f3e703c0baa2bffd0b","width":64}]},{"id":"2dM2kDJBU1wt6uszO29O0Z","name":"Bela Megale - Conversa de Bastidor","publisher":"CBN","images":[{"height":640,"url":"https:\/\/i.scdn.co\/image\/ab6765630000ba8a63abaf842fd5bf94e4756eba","width":640},{"height":300,"url":"https:\/\/i.scdn.co\/image\/ab67656300005f1f63abaf842fd5bf94e4756eba","width":300},{"height":64,"url":"https:\/\/i.scdn.co\/image\/ab6765630000f68d63abaf842fd5bf94e4756eba","width":64}]},{"id":"6bAvAAcvAWUAbwgxhbJhUi","name":"So Dramatic! with Megan Pustetto","publisher":"So Dramatic!","images":[{"height":640,"url":"https:\/\/i.scdn.co\/image\/ab6765630000ba8a003f1043d89ee45718dfd183","width":640},{"height":300,"url":"https:\/\/i.scdn.co\/image\/ab67656300005f1f003f1043d89ee45718dfd183","width":300},{"height":64,"url":"https:\/\/i.scdn.co\/image\/ab6765630000f68d003f1043d89ee45718dfd183","width":64}]},{"id":"3BRg4C52ElAD0nkGWnWLZY","name":"El Cartel de La Mega","publisher":"RCN Radio","images":[{"height":640,"url":"https:\/\/i.scdn.co\/image\/ab6765630000ba8afdb3852867e8998123028fbd","width":640},{"height":300,"url":"https:\/\/i.scdn.co\/image\/ab67656300005f1ffdb3852867e8998123028fbd","width":300},{"height":64,"url":"https:\/\/i.scdn.co\/image\/ab6765630000f68dfdb3852867e8998123028fbd","width":64}]},{"id":"58O12ASAsywYUunvgIHpq9","name":"The Mega64 Podcast","publisher":"Mega64","images":[{"height":640,"url":"https:\/\/i.scdn.co\/image\/ab6765630000ba8a747c678e5448f47fadb132c5","width":640},{"height":300,"url":"https:\/\/i.scdn.co\/image\/ab67656300005f1f747c678e5448f47fadb132c5","width":300},{"height":64,"url":"https:\/\/i.scdn.co\/image\/ab6765630000f68d747c678e5448f47fadb132c5","width":64}]},{"id":"36R4GFh1Cwn30FAGpsB2Lh","name":"Mega","publisher":"Hey Sugar Inc.","images":[{"height":640,"url":"https:\/\/i.scdn.co\/image\/ab6765630000ba8a001798e9decfb05d447c815f","width":640},{"height":300,"url":"https:\/\/i.scdn.co\/image\/ab67656300005f1f001798e9decfb05d447c815f","width":300},{"height":64,"url":"https:\/\/i.scdn.co\/image\/ab6765630000f68d001798e9decfb05d447c815f","width":64}]}],"tracks":[{"id":"1mTCbTpcM1nKkH0wGf70Zq","name":"Jagdzeit","popularity":46,"images":[{"height":640,"width":640,"url":"https:\/\/i.scdn.co\/image\/ab67616d0000b2730d149675f0468a4135e84712"},{"height":300,"width":300,"url":"https:\/\/i.scdn.co\/image\/ab67616d00001e020d149675f0468a4135e84712"},{"height":64,"width":64,"url":"https:\/\/i.scdn.co\/image\/ab67616d000048510d149675f0468a4135e84712"}],"artists":[{"id":"4tM8qmqg5cEZPHNLNQwHeb","name":"Megaherz"}],"duration_ms":258106},{"id":"1J03Vp93ybKIxfzYI4YJtL","name":"MEGALOVANIA","popularity":69,"images":[{"height":640,"width":640,"url":"https:\/\/i.scdn.co\/image\/ab67616d0000b27324edb22d068eb245a924b7f2"},{"height":300,"width":300,"url":"https:\/\/i.scdn.co\/image\/ab67616d00001e0224edb22d068eb245a924b7f2"},{"height":64,"width":64,"url":"https:\/\/i.scdn.co\/image\/ab67616d0000485124edb22d068eb245a924b7f2"}],"artists":[{"id":"57DlMWmbVIf2ssJ8QBpBau","name":"Toby Fox"}],"duration_ms":156000},{"id":"65lzRdaTSuLkNrCWcSefGi","name":"Mega Sena","popularity":59,"images":[{"height":640,"width":640,"url":"https:\/\/i.scdn.co\/image\/ab67616d0000b27340416de69dc23302dfd71a3b"},{"height":300,"width":300,"url":"https:\/\/i.scdn.co\/image\/ab67616d00001e0240416de69dc23302dfd71a3b"},{"height":64,"width":64,"url":"https:\/\/i.scdn.co\/image\/ab67616d0000485140416de69dc23302dfd71a3b"}],"artists":[{"id":"2uOlKKhuUUWlTITCYYUuIK","name":"Pablo"}],"duration_ms":230909},{"id":"48a10s0prwFVvEbGWdVhi7","name":"Mega do Akon","popularity":58,"images":[{"height":640,"width":640,"url":"https:\/\/i.scdn.co\/image\/ab67616d0000b273da035a54544f8181eabe473d"},{"height":300,"width":300,"url":"https:\/\/i.scdn.co\/image\/ab67616d00001e02da035a54544f8181eabe473d"},{"height":64,"width":64,"url":"https:\/\/i.scdn.co\/image\/ab67616d00004851da035a54544f8181eabe473d"}],"artists":[{"id":"22NFWM3F5kyI8KsRZVCSRr","name":"DJ Jonatas Felipe"},{"id":"6QshhXyQBLzoTMIfN5UZLI","name":"DogBeat"}],"duration_ms":145960},{"id":"5Q1tv4GTxP3IJeGMOKdrFO","name":"MEGAVERSE","popularity":73,"images":[{"height":640,"width":640,"url":"https:\/\/i.scdn.co\/image\/ab67616d0000b2732bca95a658fdf653a35a3710"},{"height":300,"width":300,"url":"https:\/\/i.scdn.co\/image\/ab67616d00001e022bca95a658fdf653a35a3710"},{"height":64,"width":64,"url":"https:\/\/i.scdn.co\/image\/ab67616d000048512bca95a658fdf653a35a3710"}],"artists":[{"id":"2dIgFjalVxs4ThymZ67YCE","name":"Stray Kids"}],"duration_ms":185520},{"id":"1xWnRVOZiVLkSIJbNRfiy8","name":"Mega Funk Lost","popularity":58,"images":[{"height":640,"width":640,"url":"https:\/\/i.scdn.co\/image\/ab67616d0000b2738e04e473b1ff94c5af9efddc"},{"height":300,"width":300,"url":"https:\/\/i.scdn.co\/image\/ab67616d00001e028e04e473b1ff94c5af9efddc"},{"height":64,"width":64,"url":"https:\/\/i.scdn.co\/image\/ab67616d000048518e04e473b1ff94c5af9efddc"}],"artists":[{"id":"4XZR4NawJ2XBNzaINpqrI5","name":"DJ Maninho"},{"id":"55s1nOqpHGET1gHUReBJZh","name":"Dj Dudu"},{"id":"6ulkDr2Bnu7Qlbrs5iDOF1","name":"MC Teteu"},{"id":"0f1IECbrVV952unZkzrsg2","name":"Mc Gw"}],"duration_ms":161284},{"id":"293GQJcrH6jv6Ci2qoEPKF","name":"Mega Ritmista Glaison Willians","popularity":6,"images":[{"height":640,"width":640,"url":"https:\/\/i.scdn.co\/image\/ab67616d0000b27347b44b006e76678aef549e3f"},{"height":300,"width":300,"url":"https:\/\/i.scdn.co\/image\/ab67616d00001e0247b44b006e76678aef549e3f"},{"height":64,"width":64,"url":"https:\/\/i.scdn.co\/image\/ab67616d0000485147b44b006e76678aef549e3f"}],"artists":[{"id":"0f1IECbrVV952unZkzrsg2","name":"Mc Gw"},{"id":"651jNHJzsX4ckQvURNNAIS","name":"DJ YUZAK"}],"duration_ms":167379},{"id":"2uH5OHW0QColvUbyGUl9Fh","name":"Mega do Toma","popularity":2,"images":[{"height":640,"width":640,"url":"https:\/\/i.scdn.co\/image\/ab67616d0000b273b36a76f5847ce3856a65e51f"},{"height":300,"width":300,"url":"https:\/\/i.scdn.co\/image\/ab67616d00001e02b36a76f5847ce3856a65e51f"},{"height":64,"width":64,"url":"https:\/\/i.scdn.co\/image\/ab67616d00004851b36a76f5847ce3856a65e51f"}],"artists":[{"id":"0f1IECbrVV952unZkzrsg2","name":"Mc Gw"},{"id":"2pJcXajGPboHobH4LMoYLr","name":"Dj sx"},{"id":"6xLwMXZov1Duj9fkp6ekQ3","name":"Os Taef"}],"duration_ms":167846},{"id":"5YzDr5BIEDHfmY0XfGiTXn","name":"Mega Funk Faz Macete","popularity":54,"images":[{"height":640,"width":640,"url":"https:\/\/i.scdn.co\/image\/ab67616d0000b27324581c5e747ad2eaf8efedc2"},{"height":300,"width":300,"url":"https:\/\/i.scdn.co\/image\/ab67616d00001e0224581c5e747ad2eaf8efedc2"},{"height":64,"width":64,"url":"https:\/\/i.scdn.co\/image\/ab67616d0000485124581c5e747ad2eaf8efedc2"}],"artists":[{"id":"1rpIqBtHIGInNjPbRVha5x","name":"TAIDigital"},{"id":"0f1IECbrVV952unZkzrsg2","name":"Mc Gw"},{"id":"3a5ydeAaojKa3CHWe5PVWK","name":"MC MM"}],"duration_ms":232529},{"id":"5Ud3KWvOqgzIBNkUOMXOvm","name":"Mega Arrocha 1.0","popularity":1,"images":[{"height":640,"width":640,"url":"https:\/\/i.scdn.co\/image\/ab67616d0000b273dc796268620d68df538e2eb5"},{"height":300,"width":300,"url":"https:\/\/i.scdn.co\/image\/ab67616d00001e02dc796268620d68df538e2eb5"},{"height":64,"width":64,"url":"https:\/\/i.scdn.co\/image\/ab67616d00004851dc796268620d68df538e2eb5"}],"artists":[{"id":"0f1IECbrVV952unZkzrsg2","name":"Mc Gw"},{"id":"3l4fsEzoeabsET7ddv0lZW","name":"Mc Delux"},{"id":"1DcicDOxSLsJFsqOs4QobX","name":"DJ Ralph LM"},{"id":"07MhlA3Y1Y6iDS9nKAT1cP","name":"Andr\u00e9 \u00danico no Beat"}],"duration_ms":137759}],"best_result":{"type":"artist","id":"1Yox196W7bzVNZI7RBaPnf","name":"Megadeth","popularity":71,"images":[{"url":"https:\/\/i.scdn.co\/image\/ab6761610000e5eb3f19bad1d41dceb90d8b4cf5","height":640,"width":640},{"url":"https:\/\/i.scdn.co\/image\/ab676161000051743f19bad1d41dceb90d8b4cf5","height":320,"width":320},{"url":"https:\/\/i.scdn.co\/image\/ab6761610000f1783f19bad1d41dceb90d8b4cf5","height":160,"width":160}],"artists":[{"id":"1Yox196W7bzVNZI7RBaPnf","name":"Megadeth"}]}}